[{"s": "ekstra-mini-bikini", "t": "Экстра мини бикини: выбор, стиль и сочетания", "i": "👙", "c": "nizhnee-belyo-i-kolgotki"}, {"s": "ekipirovka-pozharnogo-vklyuchaet", "t": "Экипировка пожарного: что включает полный комплект одежды", "i": "🦺", "c": "spetsodezhda"}, {"s": "eksomida-drevnegrecheskaya-odezhda", "t": "Эксомида: греческая одежда в деталях", "i": "👘", "c": "natsionalnaya-i-istoricheskaya-odezhda"}, {"s": "ekomoda-kostyumy-dlya-detej", "t": "Экомода: детские костюмы из натуральных тканей", "i": "🧸", "c": "detskaya-odezhda"}, {"s": "eko-kostyumy-dlya-detej-svoimi-rukami", "t": "Эко костюмы для детей своими руками: идеи и выкройки", "i": "🧵", "c": "rukodelie-i-diy"}, {"s": "eko-kostyum-dlya-devochki-svoimi-rukami-v-sadik", "t": "Эко костюм для девочки в садик своими руками: идеи и выкройки", "i": "🧵", "c": "rukodelie-i-diy"}, {"s": "eko-kostyumy-dlya-detej", "t": "Эко костюмы для детей: виды тканей, пошив и уход", "i": "🧸", "c": "detskaya-odezhda"}, {"s": "eko-kostyum-dlya-devochki-svoimi-rukami", "t": "Эко костюм для девочки своими руками: идеи, выкройки и материалы", "i": "🧵", "c": "rukodelie-i-diy"}, {"s": "eko-kostyum-dlya-devochki", "t": "Эко костюм для девочки: выбор ткани, выкройки и идеи", "i": "🧸", "c": "detskaya-odezhda"}, {"s": "eko-plate-svoimi-rukami", "t": "Эко платье своими руками: выкройки, ткани и мастер-класс", "i": "🧵", "c": "rukodelie-i-diy"}]