[{"s": "gandi-golovnoj-ubor", "t": "Ганди головной убор: история, виды и как сделать шапку Махатмы", "i": "👘", "c": "natsionalnaya-i-istoricheskaya-odezhda"}, {"s": "gamash-chto-eto", "t": "Гамаш что это: виды, история и правила ношения", "i": "👜", "c": "aksessuary"}, {"s": "galanterejnye-izdeliya-gost", "t": "Галантерейные изделия ГОСТ: стандарты качества и классификация", "i": "👜", "c": "aksessuary"}, {"s": "galstuk-na-rezinke-5-bukv", "t": "Галстук на резинке: как правильно называется и завязывать", "i": "👜", "c": "aksessuary"}, {"s": "galstuk-dlya-devochki-k-shkolnoj-forme-svoimi-rukami", "t": "Галстук для девочки своими руками: выкройки и мастер-класс", "i": "👜", "c": "aksessuary"}, {"s": "gangsterskaya-vecherinka-odezhda-dlya-zhenshchin-i-muzhchin", "t": "Гангстерская вечеринка: одежда для женщин и мужчин, образы", "i": "📁", "c": null}, {"s": "gangsterskij-stil-odezhdy", "t": "Гангстерский стиль одежды: как одеться в стиле 20-30-х годов", "i": "👠", "c": "stil-i-moda"}, {"s": "galstuki-k-sinemu-kostyumu", "t": "Галстуки к синему костюму: идеальные сочетания и правила стиля", "i": "🤵", "c": "pidzhaki-i-kostyumy"}, {"s": "garderob-zhenshchiny-40", "t": "Гардероб женщины 40 лет: стильные базовые вещи и правила", "i": "👠", "c": "stil-i-moda"}, {"s": "galstuk-kak-zavyazat-poshagovo", "t": "Как завязать галстук пошагово: 5 классических узлов", "i": "👜", "c": "aksessuary"}, {"s": "gamashi-chto-eto-takoe-zhenskie", "t": "Женские гамаши: что это, отличие от колготок и с чем носить", "i": "👙", "c": "nizhnee-belyo-i-kolgotki"}, {"s": "galstuk-babochka-vykrojka", "t": "Выкройка галстука-бабочки своими руками: пошаговая инструкция", "i": "👜", "c": "aksessuary"}, {"s": "garderob-zhenshchiny-posle-50-bazovye-veshchi", "t": "Гардероб женщины после 50: базовые вещи для элегантного стиля", "i": "👠", "c": "stil-i-moda"}, {"s": "gamashi-dlya-chego-nuzhny", "t": "Гамаши для чего нужны: виды, отличия от гетр и как носить", "i": "👜", "c": "aksessuary"}, {"s": "gamashi-i-getry-chem-otlichayutsya", "t": "Гамаши и гетры: в чем разница и как их носить", "i": "👜", "c": "aksessuary"}, {"s": "garderob-dlya-barbi", "t": "Гардероб для Барби: виды одежды, выкройки и стиль", "i": "🧵", "c": "rukodelie-i-diy"}, {"s": "gangster-stil-odezhdy", "t": "Гангстерский стиль одежды: история, атрибуты и правила ношения", "i": "👠", "c": "stil-i-moda"}, {"s": "gangsterskij-stil-v-odezhde-dlya-zhenshchin", "t": "Женский гангстерский стиль: одежда, образы и аксессуары", "i": "👠", "c": "stil-i-moda"}, {"s": "gajd-po-zavyazyvaniyu-galstuka", "t": "Гайд по завязыванию галстука: пошаговые схемы и секреты", "i": "👜", "c": "aksessuary"}, {"s": "gamashi-proiskhozhdenie-slova", "t": "Гамаши: происхождение слова, история и современное применение", "i": "👜", "c": "aksessuary"}, {"s": "galstuk-babochka-dlya-malchika-svoimi-rukami-vykrojka", "t": "Галстук бабочка для мальчика своими руками: выкройка и мастер-класс", "i": "🧵", "c": "rukodelie-i-diy"}, {"s": "gartery-chto-eto-takoe-i-zachem", "t": "Гартеры: что это, зачем нужны и как носить", "i": "👜", "c": "aksessuary"}, {"s": "galstuk-na-ruke", "t": "Галстук на руке: как завязать, когда носить и что означает", "i": "👜", "c": "aksessuary"}, {"s": "gangstery-zhenshchiny-obraz", "t": "Образ гангстера: женский стиль, костюмы и детали", "i": "👠", "c": "stil-i-moda"}, {"s": "galstuk-zavyazat-na-ruke", "t": "Как завязать галстук на руке: пошаговая инструкция", "i": "👜", "c": "aksessuary"}, {"s": "galstuk-na-rezinke-5", "t": "Галстук на резинке: виды, размеры, как завязывать и носить", "i": "👜", "c": "aksessuary"}, {"s": "galstuk-sshit-svoimi-rukami-vykrojka", "t": "Галстук своими руками: выкройка и пошаговая инструкция", "i": "👜", "c": "aksessuary"}, {"s": "galife-shtany-zhenskie", "t": "Женские брюки галифе: с чем носить и кому идут", "i": "🩳", "c": "bryuki-i-shorty"}, {"s": "galstuk-babochka-dlya-igrushki-kryuchkom", "t": "Галстук-бабочка крючком для игрушки: схема и описание", "i": "🧵", "c": "rukodelie-i-diy"}, {"s": "garderob-40-letnej-zhenshchiny", "t": "Гардероб 40 летней женщины: стиль, капсула и ошибки", "i": "👠", "c": "stil-i-moda"}, {"s": "galstuk-pravilno-zavyazat", "t": "Как правильно завязать галстук: пошаговая инструкция", "i": "👜", "c": "aksessuary"}, {"s": "gamashi-kak-vyglyadyat", "t": "Как выглядят гамаши: фото, виды и с чем носить", "i": "👙", "c": "nizhnee-belyo-i-kolgotki"}, {"s": "gamasha-chto-eto", "t": "Гамаша: что это, история и как носить. Виды и отличия", "i": "👟", "c": "obuv"}, {"s": "gamashi-dlya-chego", "t": "Гамаши для чего: история, виды, с чем носить", "i": "👜", "c": "aksessuary"}, {"s": "gangsterskij-stil-v-odezhde-zhenshchiny", "t": "Гангстерский стиль в одежде женщины: как создать образ", "i": "👠", "c": "stil-i-moda"}, {"s": "gangsterskij-stil-zhenshchin", "t": "Гангстерский стиль в женской одежде: как создать дерзкий образ", "i": "👠", "c": "stil-i-moda"}, {"s": "garderob-kukly-odezhda-dlya-barbi", "t": "Гардероб куклы: одежда для Барби своими руками и готовые образы", "i": "🧵", "c": "rukodelie-i-diy"}, {"s": "galstuki-kak-zavyazat", "t": "Как завязать галстук: пошаговые схемы и виды узлов", "i": "👜", "c": "aksessuary"}, {"s": "galstuk-babochka-iz-foamirana", "t": "Галстук бабочка из фоамирана: пошаговая инструкция", "i": "🧵", "c": "rukodelie-i-diy"}, {"s": "garderob-zhenshchiny-40-let", "t": "Гардероб женщины 40 лет: стиль, капсула и базовые вещи", "i": "👠", "c": "stil-i-moda"}, {"s": "galstuk-svoimi-rukami", "t": "Галстук своими руками: выкройки, пошив и выбор ткани", "i": "🧵", "c": "rukodelie-i-diy"}, {"s": "galstuk-babochka-svoimi-rukami-iz-lenty", "t": "Галстук-бабочка своими руками из ленты: мастер-класс", "i": "👜", "c": "aksessuary"}, {"s": "galstuk-detskij-svoimi-rukami", "t": "Детский галстук своими руками: выкройки и мастер-класс", "i": "🧵", "c": "rukodelie-i-diy"}, {"s": "galstuk-na-rezinke-kak-zavyazat", "t": "Галстук на резинке: как завязать, надеть и носить правильно", "i": "👜", "c": "aksessuary"}, {"s": "galstuk-babochka-svoimi-rukami", "t": "Галстук бабочка своими руками: выкройки, ткани, пошаговый пошив", "i": "🧵", "c": "rukodelie-i-diy"}, {"s": "gangstery-stil-odezhdy", "t": "Стиль гангстер: одежда, аксессуары и создание образа", "i": "👠", "c": "stil-i-moda"}, {"s": "galstuk-sshit-svoimi-rukami", "t": "Как сшить галстук своими руками: пошаговая инструкция и выкройки", "i": "🧵", "c": "rukodelie-i-diy"}, {"s": "galife-chto-eto", "t": "Галифе что это: особенности кроя, история и с чем носить", "i": "🩳", "c": "bryuki-i-shorty"}, {"s": "gamashi-eto-chto-takoe", "t": "Гамаши: что это такое, история, виды и как их носить", "i": "👙", "c": "nizhnee-belyo-i-kolgotki"}, {"s": "galstuk-babochka-svoimi-rukami-dlya-malchika", "t": "Галстук бабочка своими руками для мальчика: выкройки и мастер-класс", "i": "👜", "c": "aksessuary"}, {"s": "galstuk-na-rezinke", "t": "Галстук на резинке: как завязать и с чем носить", "i": "👜", "c": "aksessuary"}, {"s": "galstuk-zavyazat-skhema-prostoj-dlya-muzhchin-poshagovo-klassicheskij", "t": "Как завязать классический галстук: простая пошаговая схема", "i": "👜", "c": "aksessuary"}, {"s": "gamashi-otkuda-slovo", "t": "Гамаши: откуда слово и история происхождения формы", "i": "🪖", "c": "voennaya-forma"}, {"s": "gamashi-eto-chto", "t": "Гамаши: что это такое, с чем носить и как вязать", "i": "👜", "c": "aksessuary"}]