[{"s": "pyzhikovye-shapki-iz-chego", "t": "Пыжиковые шапки: из чего делают, свойства и уход", "i": "🧢", "c": "golovnye-ubory"}, {"s": "pyshnye-bantiki-iz-atlasnykh-lent", "t": "Пышные бантики из атласных лент: пошаговый мастер-класс", "i": "🧵", "c": "rukodelie-i-diy"}, {"s": "pyshnyj-podyubnik-svoimi-rukami", "t": "Пышный подъюбник своими руками: пошаговая инструкция и выкройки", "i": "🧵", "c": "rukodelie-i-diy"}, {"s": "pyshnye-platya-na-vypusknoj-9-klass", "t": "Пышные платья на выпускной 9 класс: выбор фасона и ткани", "i": "👗", "c": "platya-i-sarafany"}, {"s": "pyzhik-chto-eto-za-zver", "t": "Пыжик что это за зверь: мех, виды и свойства", "i": "🧥", "c": "verkhnyaya-odezhda"}, {"s": "pyshnoe-plate-dlya-kukly-kryuchkom", "t": "Пышное платье для куклы крючком: схемы и инструкции", "i": "🧵", "c": "rukodelie-i-diy"}, {"s": "pyzhikovye-shapki-iz-chego-delayut", "t": "Из чего делают пыжиковые шапки: материалы и технологии", "i": "📁", "c": null}, {"s": "pyshnaya-yubka-iz-setki", "t": "Пышная юбка из сетки: с чем носить, как сшить и ухаживать", "i": "👚", "c": "yubki"}, {"s": "pyatno-na-kurtke-chem-vyvesti", "t": "Пятно на куртке: чем вывести? 15 проверенных способов", "i": "🧥", "c": "verkhnyaya-odezhda"}, {"s": "pyshnyj-bant-iz-atlasnoj-lenty-svoimi-rukami-poshagovoe", "t": "Пышный бант из атласной ленты своими руками пошаговое фото", "i": "🧵", "c": "rukodelie-i-diy"}, {"s": "pyatnovyvoditel-dlya-membrannoj-odezhdy", "t": "Пятновыводитель для мембранной одежды: выбор и применение", "i": "🧼", "c": "ukhod-za-odezhdoj"}, {"s": "pyat-zvezd-na-pogonakh-kakoe-zvanie", "t": "Пять звезд на погонах: какое звание и как отличить", "i": "🪖", "c": "voennaya-forma"}, {"s": "pyzhikovye-shapki-iz-kakogo-mekha", "t": "Пыжиковые шапки: из какого меха делают и как отличить", "i": "🧢", "c": "golovnye-ubory"}, {"s": "pyshnaya-yubka-pachka", "t": "Пышная юбка пачка: виды, сочетания и как сшить своими руками", "i": "👚", "c": "yubki"}, {"s": "pyatna-ot-kleya-na-odezhde-chem-vyvesti", "t": "Чем вывести пятна от клея с одежды: проверенные способы", "i": "🧼", "c": "ukhod-za-odezhdoj"}, {"s": "pyatka-noska-spitsami-poshagovo", "t": "Вывязывание пятки и носка спицами: пошаговый мастер-класс", "i": "🧵", "c": "rukodelie-i-diy"}, {"s": "pyshnoe-balnoe-plate", "t": "Пышное бальное платье: выбор фасона, ткани и аксессуаров", "i": "👗", "c": "platya-i-sarafany"}, {"s": "pyshnaya-yubka-kak-nazyvaetsya", "t": "Как называется пышная юбка: гид по фасонам и стилям", "i": "👚", "c": "yubki"}, {"s": "pylevykh-tsvetov-venochek", "t": "Пылевых цветов веночек: значение, уход и сочетание с одеждой", "i": "👜", "c": "aksessuary"}, {"s": "pyshnaya-yubka-dlya-devochki-svoimi-rukami", "t": "Пышная юбка для девочки своими руками: пошаговый мастер-класс", "i": "🧵", "c": "rukodelie-i-diy"}, {"s": "pyatka-kryuchkom-noski", "t": "Пятка крючком носки: пошаговая инструкция и схемы", "i": "🧵", "c": "rukodelie-i-diy"}, {"s": "pyatka-noska-kryuchkom", "t": "Пятка носка крючком: схемы, способы вязания и ошибки", "i": "🧵", "c": "rukodelie-i-diy"}, {"s": "pyshnaya-skladka-na-yubke", "t": "Пышная складка на юбке: виды, выкройки и секреты пошива", "i": "👚", "c": "yubki"}, {"s": "pyzhiki-chto-eto-takoe", "t": "Пыжики: что это такое в вязании и шитье", "i": "🧢", "c": "golovnye-ubory"}, {"s": "pyatka-noska-spitsami", "t": "Пятка носка спицами: пошаговый мастер-класс и схемы", "i": "🧵", "c": "rukodelie-i-diy"}, {"s": "pyzhikovaya-shapka-iz-kogo", "t": "Пыжиковая шапка: из какого меха и как отличить", "i": "🧢", "c": "golovnye-ubory"}, {"s": "pyatno-ot-mashinnogo-masla", "t": "Как удалить пятно от машинного масла: эффективные методы", "i": "🧼", "c": "ukhod-za-odezhdoj"}, {"s": "pyat-zvezd-eto-kakoe-zvanie", "t": "Пять звёзд: какое это звание в армии РФ и других странах", "i": "🪖", "c": "voennaya-forma"}, {"s": "pyzhikovaya-shapka-iz-kakogo-mekha-sdelana", "t": "Из какого меха сделана пыжиковая шапка: история и виды", "i": "🧢", "c": "golovnye-ubory"}, {"s": "pyshnoe-koktejlnoe-plate", "t": "Пышное коктейльное платье: фасоны, стиль и секреты выбора", "i": "👗", "c": "platya-i-sarafany"}, {"s": "pyshnyj-bant-svoimi-rukami", "t": "Пышный бант своими руками: пошаговая инструкция и секреты", "i": "🧵", "c": "rukodelie-i-diy"}, {"s": "pyatka-kak-vyazat-spitsami", "t": "Пятка как вязать спицами: пошаговый гид", "i": "🧵", "c": "rukodelie-i-diy"}, {"s": "pyzhikovaya-shapka-eto", "t": "Пыжиковая шапка это: что такое, кому идет и как носить", "i": "🧢", "c": "golovnye-ubory"}, {"s": "pyatna-ot-mashinnogo-masla-na-odezhde-chem-vyvesti", "t": "Пятна от машинного масла на одежде: чем вывести и как отстирать", "i": "🧼", "c": "ukhod-za-odezhdoj"}, {"s": "pyzhik-shapka-iz-kakogo-mekha", "t": "Пыжик шапка из какого меха: отличия, фото, как отличить", "i": "🧢", "c": "golovnye-ubory"}, {"s": "pyshnaya-yubka-iz-fatina-dlya-devochki-svoimi-rukami", "t": "Пышная юбка из фатина для девочки своими руками: пошагово", "i": "🧵", "c": "rukodelie-i-diy"}, {"s": "pyat-zvezd-na-pogonakh-zvanie-v-armii", "t": "Пять звезд на погонах: звание в армии и история формы", "i": "🪖", "c": "voennaya-forma"}, {"s": "pyshnye-banty-iz-atlasnoj-lenty", "t": "Пышные банты из атласной ленты: пошаговый мастер-класс и идеи", "i": "🧵", "c": "rukodelie-i-diy"}, {"s": "pyshnye-banty-iz-atlasnykh-lent-svoimi-rukami", "t": "Пышные банты из атласных лент своими руками: мастер-класс", "i": "👜", "c": "aksessuary"}, {"s": "pyat-zvezd-na-pogonakh-zvanie-v-politsii", "t": "Пять звёзд на погонах полиции: звание, форма и отличия", "i": "🪖", "c": "voennaya-forma"}, {"s": "pyat-zvezd-na-pogonakh-zvanie", "t": "Пять звезд на погонах: звание генерала армии в РФ", "i": "🪖", "c": "voennaya-forma"}, {"s": "pyat-zvezd-na-pogonakh", "t": "Пять звёзд на погонах: генеральское звание и знаки различия", "i": "🪖", "c": "voennaya-forma"}, {"s": "pyatka-fliglya-spitsami-opisanie", "t": "Пятка флигля спицами: описание, схемы и секреты вязания", "i": "🧵", "c": "rukodelie-i-diy"}, {"s": "pyshnoe-plate-nevesty", "t": "Пышное платье невесты: выбор, фасоны и сочетания", "i": "👗", "c": "platya-i-sarafany"}, {"s": "pyatno-ot-laka-dlya-nogtej-na-odezhde-chem-vyvesti", "t": "Пятно от лака для ногтей на одежде: чем вывести", "i": "🧼", "c": "ukhod-za-odezhdoj"}, {"s": "pyshnaya-yubka-s-chem-nosit", "t": "С чем носить пышную юбку: сочетания, советы и тренды", "i": "👚", "c": "yubki"}, {"s": "pyshki-v-dzhinsakh", "t": "Пышки в джинсах: как скрыть живот и полноту", "i": "👖", "c": "dzhinsy"}, {"s": "pyshnaya-yubka-solntse", "t": "Пышная юбка солнце: с чем носить, выкройки и секреты стиля", "i": "👚", "c": "yubki"}, {"s": "pyshnoe-rozovoe-plate-zhenskoe", "t": "Пышное розовое платье женское: выбор, фасоны и сочетания", "i": "👗", "c": "platya-i-sarafany"}, {"s": "pyshnye-bantiki-iz-atlasnykh-lent-svoimi-rukami", "t": "Пышные бантики из атласных лент своими руками: мастер-класс", "i": "🧵", "c": "rukodelie-i-diy"}, {"s": "pyshnye-modeli-v-nizhnem-bele", "t": "Пышные модели в нижнем белье: как выбрать, фасоны, ткани", "i": "👙", "c": "nizhnee-belyo-i-kolgotki"}, {"s": "pyzhikovaya-shapka-iz-chego", "t": "Пыжиковая шапка: из чего делают, свойства и отличия", "i": "🧢", "c": "golovnye-ubory"}, {"s": "pyshnye-banty-svoimi-rukami", "t": "Пышные банты своими руками: пошаговый мастер-класс", "i": "🧵", "c": "rukodelie-i-diy"}, {"s": "pyshnyj-podyubnik-iz-fatina-vykrojka", "t": "Выкройка пышного подъюбника из фатина: пошаговое руководство", "i": "🧵", "c": "rukodelie-i-diy"}, {"s": "pyzhikovye-shapki-iz-chego-sdelany", "t": "Пыжиковые шапки: из чего сделаны, виды и отличия", "i": "🧢", "c": "golovnye-ubory"}, {"s": "pyatno-ot-mashinnogo-masla-na-odezhde-chem-vyvesti", "t": "Пятно от машинного масла на одежде: чем вывести безопасно", "i": "🧼", "c": "ukhod-za-odezhdoj"}, {"s": "pyzhik-eto-detenysh-kakogo-zhivotnogo", "t": "Пыжик: детеныш какого животного и одежда из шкуры", "i": "🧥", "c": "verkhnyaya-odezhda"}, {"s": "pyatno-na-dzhinsakh-kak-vyvesti", "t": "Пятно на джинсах: как вывести в домашних условиях", "i": "🧼", "c": "ukhod-za-odezhdoj"}, {"s": "pyshnaya-yubka-do-kolen", "t": "Пышная юбка до колен: с чем носить, кому идет и как сшить", "i": "👚", "c": "yubki"}, {"s": "pyzhik-mekh-iz-kakogo-zverka", "t": "Пыжик мех: из какого зверька и как отличить от норки", "i": "🧢", "c": "golovnye-ubory"}, {"s": "pyatna-ot-mashinnogo-masla-na-odezhde-chem-vyvesti-doma", "t": "Пятна от машинного масла на одежде: чем вывести дома", "i": "🧼", "c": "ukhod-za-odezhdoj"}, {"s": "pyshnaya-skladka-na-yubke-3-bukvy", "t": "Пышная складка на юбке 3 буквы: ответ на кроссворд и виды", "i": "👚", "c": "yubki"}, {"s": "pyzhik-eto-chto", "t": "Пыжик это что: виды, отличия от шапки-ушанки и применение", "i": "🧢", "c": "golovnye-ubory"}, {"s": "pyatnovyvoditel-ot-mashinnogo-masla-s-odezhdy", "t": "Пятновыводитель от машинного масла: как отстирать с одежды", "i": "🧼", "c": "ukhod-za-odezhdoj"}, {"s": "pyshnaya-yubka-iz-fatina-s-chem-nosit", "t": "Пышная юбка из фатина: с чем носить и как сочетать", "i": "👚", "c": "yubki"}, {"s": "pyshnyj-bant-iz-atlasnoj-lenty", "t": "Пышный бант из атласной ленты: пошаговый мастер-класс", "i": "🧵", "c": "rukodelie-i-diy"}, {"s": "pyshnye-yubki-dlya-zhenshchin", "t": "Пышные юбки для женщин: фасоны, сочетания и выкройки", "i": "👚", "c": "yubki"}, {"s": "pyshnye-banty-iz-atlasnykh-lent", "t": "Пышные банты из атласных лент: пошаговые мастер-классы и идеи", "i": "👜", "c": "aksessuary"}, {"s": "pyatnovyvoditel-ot-kraski-na-odezhde", "t": "Чем отмыть краску с одежды: средства для разных тканей", "i": "🧼", "c": "ukhod-za-odezhdoj"}, {"s": "pyshnoe-bordovoe-plate", "t": "Пышное бордовое платье: с чем носить и кому идёт", "i": "👗", "c": "platya-i-sarafany"}]