[{"s": "skhema-vyazaniya-kardigana-spitsami-dlya-zhenshchin-s-opisaniem", "t": "Схема вязания кардигана спицами для женщин: пошаговое описание", "i": "🧵", "c": "rukodelie-i-diy"}, {"s": "skhemy-vyazaniya-spitsami-azhurnykh-uzorov-s-opisaniem-dlya-zhenskoj-kofty", "t": "Ажурные узоры спицами для женской кофты: схемы и описание", "i": "🧵", "c": "rukodelie-i-diy"}, {"s": "skolko-spits-nuzhno-dlya-vyazaniya-noskov", "t": "Сколько спиц нужно для вязания носков: выбор инструментов", "i": "🧵", "c": "rukodelie-i-diy"}, {"s": "skolko-zvezd-u-admirala", "t": "Сколько звезд у адмирала: все знаки различия по рангам", "i": "🪖", "c": "voennaya-forma"}, {"s": "skolko-zvezd-u-ofitsera-na-pogonakh", "t": "Сколько звезд у офицера на погонах: знаки различия по званиям", "i": "🪖", "c": "voennaya-forma"}, {"s": "skhema-shali-spitsami", "t": "Схема шали спицами: подробный мастер-класс и узоры", "i": "🧵", "c": "rukodelie-i-diy"}, {"s": "skhema-kapyushona-spitsami", "t": "Схема капюшона спицами: подробный мастер-класс", "i": "🧵", "c": "rukodelie-i-diy"}, {"s": "skhema-vyazaniya-kryuchkom-sviter", "t": "Схема вязания крючком свитер: от мерок до идеальной посадки", "i": "🧵", "c": "rukodelie-i-diy"}, {"s": "skhema-vyazaniya-noskov-kryuchkom-dlya-nachinayushchikh", "t": "Схема вязания носков крючком для начинающих: пошагово", "i": "🧵", "c": "rukodelie-i-diy"}, {"s": "skhema-zavyazyvaniya-shnurkov", "t": "Схема завязывания шнурков: 10 способов для обуви и стиля", "i": "👜", "c": "aksessuary"}, {"s": "skhemy-dlya-vyazaniya-koft", "t": "Схемы для вязания кофт: от простых узоров до сложных моделей", "i": "🧶", "c": "kofty-i-svitery"}, {"s": "skhemy-dlya-vyazaniya-spitsami-s-opisaniem-i-skhemami-dlya-zhenshchin-modeli-koftochek", "t": "Схемы вязания кофточек спицами для женщин: модели и описание", "i": "🧵", "c": "rukodelie-i-diy"}, {"s": "skolko-sokhnet-kraska-dlya-kozhi", "t": "Сколько сохнет краска для кожи: время, факторы и советы", "i": "🧵", "c": "rukodelie-i-diy"}, {"s": "skhemy-zavyazyvaniya-galstuka", "t": "Схемы завязывания галстука: пошаговые инструкции и секреты", "i": "👜", "c": "aksessuary"}, {"s": "skandinavskij-stil-v-odezhde-dlya-zhenshchin", "t": "Скандинавский стиль в одежде для женщин: гид по созданию капсулы", "i": "👠", "c": "stil-i-moda"}, {"s": "skhema-babochki-iz-bisera-krestikom", "t": "Схема бабочки из бисера крестиком: пошаговый мастер-класс", "i": "🧵", "c": "rukodelie-i-diy"}, {"s": "skhema-vyazaniya-konverta-dlya-novorozhdennogo-spitsami-s-kapyushonom", "t": "Схема вязания конверта для новорожденного спицами с капюшоном", "i": "🧵", "c": "rukodelie-i-diy"}, {"s": "skhemy-vyazaniya-spitsami-dlya-kardigana", "t": "Схемы вязания спицами для кардигана: от выбора пряжи до сборки", "i": "🧵", "c": "rukodelie-i-diy"}, {"s": "skolko-uteplitelya-dolzhno-byt-v-zimnej-detskoj-odezhde", "t": "Сколько утеплителя должно быть в зимней детской одежде: нормы грамм", "i": "🧸", "c": "detskaya-odezhda"}, {"s": "skhema-i-opisanie-vyazanykh-koft-dlya-zhenshchin-spitsami", "t": "Схемы и описание вязаных кофт для женщин: руководство", "i": "🧵", "c": "rukodelie-i-diy"}, {"s": "skhema-platka-kryuchkom-treugolnogo", "t": "Схема платка крючком треугольного: пошаговый мастер-класс", "i": "🧵", "c": "rukodelie-i-diy"}, {"s": "skhema-vyazaniya-manishka-spitsami", "t": "Схема вязания манишки спицами: пошаговый мастер-класс", "i": "🧵", "c": "rukodelie-i-diy"}, {"s": "skhema-vyazaniya-zhileta-kryuchkom", "t": "Схема вязания жилета крючком: подробный мастер-класс", "i": "🧵", "c": "rukodelie-i-diy"}, {"s": "skolko-zvezd-u-generalov", "t": "Сколько звезд у генералов: звания и погоны", "i": "🪖", "c": "voennaya-forma"}, {"s": "skolko-zvezdochek-u-majora", "t": "Сколько звездочек у майора: погоны и знаки различия", "i": "🪖", "c": "voennaya-forma"}, {"s": "skhema-svitera-kryuchkom", "t": "Схема свитера крючком: построение, расчеты и вязание", "i": "📁", "c": null}, {"s": "skhema-vyazaniya-detskogo-kombinezona-spitsami-0-6", "t": "Схема вязания детского комбинезона спицами 0-6 мес: пошагово", "i": "🧵", "c": "rukodelie-i-diy"}, {"s": "skhema-dlya-vyazaniya-svitera-kryuchkom", "t": "Схема для вязания свитера крючком: пошаговая инструкция", "i": "📁", "c": null}, {"s": "skhema-vyazaniya-azhurnykh-uzorov", "t": "Схема вязания ажурных узоров: от расшифровки до идеального полотна", "i": "🧵", "c": "rukodelie-i-diy"}, {"s": "skinni-dzhinsy-dlya-muzhchin", "t": "Мужские скинни джинсы: как выбрать и с чем носить", "i": "👖", "c": "dzhinsy"}, {"s": "skolko-zvezd-na-pogonakh-u-starshego-lejtenanta", "t": "Сколько звезд на погонах у старшего лейтенанта: описание", "i": "🪖", "c": "voennaya-forma"}, {"s": "skhema-vyazaniya-kryuchkom-babochki", "t": "Схема вязания крючком бабочки: пошаговый мастер-класс", "i": "🧵", "c": "rukodelie-i-diy"}, {"s": "skhema-vyazaniya-kryuchkom-kofty-dlya-zhenshchin", "t": "Схема вязания крючком кофты для женщин: пошаговый урок", "i": "🧶", "c": "kofty-i-svitery"}, {"s": "skhema-vyazaniya-zhiletki-kryuchkom", "t": "Схема вязания жилетки крючком: пошаговая инструкция и узоры", "i": "🧵", "c": "rukodelie-i-diy"}, {"s": "skhemy-vyazaniya-koftochek", "t": "Схемы вязания кофточек: выбор узоров и техник", "i": "🧵", "c": "rukodelie-i-diy"}, {"s": "skhemy-vyazaniya-odezhdy-dlya-kukol", "t": "Схемы вязания одежды для кукол: инструкции, узоры и лайфхаки", "i": "🧵", "c": "rukodelie-i-diy"}, {"s": "skinni-dzhinsy-na-muzhike", "t": "Скинни джинсы на мужчине: как носить и сочетать", "i": "👖", "c": "dzhinsy"}, {"s": "skladki-na-yubke-5", "t": "Складки на юбке: виды, построение и с чем носить", "i": "👚", "c": "yubki"}, {"s": "skolko-zvezd-u-generala-majora-na-pogonakh", "t": "Сколько звезд у генерала-майора: погоны РФ и знаки различия", "i": "🪖", "c": "voennaya-forma"}, {"s": "skolko-zvezd-na-pogonakh-armejskogo-kapitana", "t": "Сколько звезд на погонах армейского капитана: знаки различия", "i": "🪖", "c": "voennaya-forma"}, {"s": "skolko-zvezd-u-polkovnika-na-pogonakh", "t": "Сколько звезд у полковника на погонах: описание знаков различия", "i": "🪖", "c": "voennaya-forma"}, {"s": "skhema-vyazaniya-detskogo-kombinezona-spitsami-6-9", "t": "Схема вязания детского комбинезона спицами: размеры 6-9 месяцев", "i": "🧵", "c": "rukodelie-i-diy"}, {"s": "skhema-vyazaniya-odezhdy-dlya-kukol", "t": "Схема вязания одежды для кукол: пошаговые инструкции и узоры", "i": "🧵", "c": "rukodelie-i-diy"}, {"s": "skhema-vyazaniya-spitsami-kapor", "t": "Схема вязания спицами капор: пошаговая инструкция", "i": "🧵", "c": "rukodelie-i-diy"}, {"s": "skolko-medalej-v-ryad-mozhno-veshat", "t": "Сколько медалей в ряд вешать: нормы ношения наград", "i": "🪖", "c": "voennaya-forma"}, {"s": "skolko-tkani-nado-na-sarafan", "t": "Сколько ткани надо на сарафан: точный расчет по фасонам", "i": "👗", "c": "platya-i-sarafany"}, {"s": "skolko-tkani-nuzhno-na-dzhinsy", "t": "Сколько ткани нужно на джинсы: расход для разных фасонов", "i": "👖", "c": "dzhinsy"}, {"s": "skafandr-svoimi-rukami", "t": "Скафандр своими руками: выкройка, материалы и пошив костюма", "i": "🧵", "c": "rukodelie-i-diy"}, {"s": "skazochnyj-kostyum-svoimi-rukami", "t": "Сказочный костюм своими руками: идеи, выкройки, мастер-классы", "i": "🧵", "c": "rukodelie-i-diy"}, {"s": "skhema-noskov-kryuchkom", "t": "Схема носков крючком: пошаговый мастер-класс и расчет", "i": "🧵", "c": "rukodelie-i-diy"}, {"s": "skhema-vyazaniya-baktusa", "t": "Схема вязания бактуса спицами: подробная инструкция", "i": "🧣", "c": "sharfy-i-platki"}, {"s": "skhema-vyazaniya-shapki-kryuchkom-dlya-zhenshchin", "t": "Схема вязания шапки крючком для женщин: пошаговый мастер-класс", "i": "🧵", "c": "rukodelie-i-diy"}, {"s": "skhemy-uzorov-dlya-vyazaniya-spitsami-s-opisaniem-dlya-zhenshchin-dlya-koft", "t": "Схемы узоров спицами для женских кофт: описание и фото", "i": "🧵", "c": "rukodelie-i-diy"}, {"s": "skhemy-uzorov-shali-kryuchkom", "t": "Схемы узоров шали крючком: от простых до ажурных", "i": "🧵", "c": "rukodelie-i-diy"}, {"s": "skolko-medalej-v-odnom-ryadu-na-paradnom-kitele", "t": "Сколько медалей в ряду на кителе: нормы и правила", "i": "🪖", "c": "voennaya-forma"}, {"s": "skolko-zvezd-u-starshego-praporshchika", "t": "Сколько звезд у старшего прапорщика: знаки различия и правила ношения", "i": "🪖", "c": "voennaya-forma"}, {"s": "skolko-zvezdochek-u-praporshchika-na-pogonakh", "t": "Сколько звездочек у прапорщика на погонах: знаки различия", "i": "🪖", "c": "voennaya-forma"}, {"s": "skhema-koftochki-kryuchkom", "t": "Схема кофточки крючком: подробный мастер-класс для новичков", "i": "🧶", "c": "kofty-i-svitery"}, {"s": "skhema-vyazaniya-shali-kryuchkom-dlya-nachinayushchikh", "t": "Схема вязания шали крючком для начинающих: пошаговый урок", "i": "🧵", "c": "rukodelie-i-diy"}, {"s": "skrytyj-shov-na-dzhinsakh", "t": "Скрытый шов на джинсах: виды, способы обработки и стиль", "i": "👖", "c": "dzhinsy"}, {"s": "skhemy-vorotnichkov-kryuchkom", "t": "Схемы воротничков крючком: схемы, узоры и мастер-классы", "i": "🧵", "c": "rukodelie-i-diy"}, {"s": "skhema-vyazaniya-detskogo-kardigana", "t": "Схема вязания детского кардигана: пошаговая инструкция", "i": "🧵", "c": "rukodelie-i-diy"}, {"s": "skhema-vyazaniya-shlyapy-kryuchkom", "t": "Схема вязания шляпы крючком: пошаговый мастер-класс", "i": "🧵", "c": "rukodelie-i-diy"}, {"s": "skinny-dzhinsy-muzhskie-chto-eto", "t": "Мужские джинсы скинни: что это, кому идут и с чем носить", "i": "👖", "c": "dzhinsy"}, {"s": "skolko-lychek-u-mladshego-serzhanta", "t": "Сколько лычек у младшего сержанта: нормы погон", "i": "🪖", "c": "voennaya-forma"}, {"s": "skolko-pryazhi-nuzhno-na-shal-kryuchkom", "t": "Расход пряжи на шаль крючком: точный расчет по размеру и узору", "i": "🧵", "c": "rukodelie-i-diy"}, {"s": "skolko-vremeni-nuzhno-kipyatit-bele-chtoby-ono-otbelit", "t": "Сколько времени кипятить белье для отбеливания: время по тканям", "i": "🧼", "c": "ukhod-za-odezhdoj"}, {"s": "skhema-dlya-palantina-spitsami", "t": "Схема для палантина спицами: узоры, инструкции и советы", "i": "🧣", "c": "sharfy-i-platki"}, {"s": "skhema-pleteniya-babochki-iz-bisera", "t": "Схема плетения бабочки из бисера: пошаговая инструкция", "i": "🧵", "c": "rukodelie-i-diy"}, {"s": "skhema-vyazaniya-detskoj-shapochki-spitsami", "t": "Схема вязания детской шапочки спицами: мастер-класс", "i": "🧵", "c": "rukodelie-i-diy"}, {"s": "skhema-vyazaniya-shalej", "t": "Схема вязания шалей: пошаговые инструкции и узоры", "i": "🧵", "c": "rukodelie-i-diy"}, {"s": "skhemy-baktusov-kryuchkom", "t": "Схемы бактусов крючком: узоры, инструкции и фото для новичков", "i": "🧵", "c": "rukodelie-i-diy"}, {"s": "skhemy-kryuchkom-iz-shnura", "t": "Схемы крючком из шнура: идеи и узоры для аксессуаров", "i": "🧵", "c": "rukodelie-i-diy"}, {"s": "skolko-den-samye-plotnye-kolgotki", "t": "Сколько ден самые плотные колготки: 200, 300 или 500?", "i": "👙", "c": "nizhnee-belyo-i-kolgotki"}, {"s": "skolko-karmanov-dolzhny-imet-klassicheskie-dzhinsy", "t": "Сколько карманов у классических джинсов: стандарты и виды", "i": "👖", "c": "dzhinsy"}, {"s": "skolko-sm-zvezdy-na-pogonakh-lejtenanta", "t": "Сколько см звезды на погонах лейтенанта: размеры и нормы", "i": "🪖", "c": "voennaya-forma"}, {"s": "skolko-zvezdochek-u-praporshchika", "t": "Звёзды на погонах прапорщика: сколько штук по уставу РФ", "i": "🪖", "c": "voennaya-forma"}, {"s": "skhemy-vyazaniya-kosynki-kryuchkom", "t": "Схемы вязания косынки крючком: от простого к сложному", "i": "🧢", "c": "golovnye-ubory"}, {"s": "skhema-kupalnika-kryuchkom", "t": "Схема купальника крючком: пошаговая инструкция", "i": "🧵", "c": "rukodelie-i-diy"}, {"s": "skhema-shali-kryuchkom-s-ugla", "t": "Схема шали крючком с угла: мастер-класс и узоры", "i": "🧵", "c": "rukodelie-i-diy"}, {"s": "skolko-zvezd-u-kapitana", "t": "Сколько звезд у капитана? Погоны и звания в армии РФ", "i": "🪖", "c": "voennaya-forma"}, {"s": "skolko-zvezdochek-u-kapitana-na-pogonakh", "t": "Сколько звездочек у капитана на погонах: знаки различия", "i": "🪖", "c": "voennaya-forma"}, {"s": "skachat-vykrojku-korseta", "t": "Как скачать выкройку корсета: руководство и советы", "i": "🧵", "c": "rukodelie-i-diy"}, {"s": "skhema-babochki-iz-bisera", "t": "Схема бабочки из бисера: пошаговый мастер-класс и техники", "i": "🧵", "c": "rukodelie-i-diy"}, {"s": "skhemy-vyazaniya-kryuchkom-kosynok", "t": "Схемы вязания крючком косынок: пошаговые инструкции", "i": "🧵", "c": "rukodelie-i-diy"}, {"s": "skhema-zhiletki-kryuchkom-dlya-zhenshchin", "t": "Схема жилетки крючком для женщин: лучшие модели и описание", "i": "🧵", "c": "rukodelie-i-diy"}, {"s": "skhema-vyazaniya-bereta", "t": "Схема вязания берета спицами и крючком: пошагово", "i": "🧵", "c": "rukodelie-i-diy"}, {"s": "skolko-kipyatit-belye-noski", "t": "Сколько кипятить белые носки: время и способы отбеливания", "i": "🧼", "c": "ukhod-za-odezhdoj"}, {"s": "skolko-nuzhno-pryazhi-na-noski", "t": "Сколько нужно пряжи на носки: точный расчет по размеру", "i": "🧵", "c": "rukodelie-i-diy"}, {"s": "skhema-vyazaniya-bereta-kryuchkom", "t": "Схема вязания берета крючком: пошаговая инструкция", "i": "🧵", "c": "rukodelie-i-diy"}, {"s": "skhema-kosynok-kryuchkom", "t": "Схема косынок крючком: 10 мастер-классов и схемы", "i": "🧵", "c": "rukodelie-i-diy"}, {"s": "skhema-vyazaniya-noskov-spitsami-dlya-nachinayushchikh", "t": "Схема вязания носков спицами для начинающих: пошагово", "i": "🧵", "c": "rukodelie-i-diy"}, {"s": "skhema-vyazaniya-zhenskogo-kardigana-spitsami", "t": "Схема вязания женского кардигана спицами: от выбора пряжи до сборки", "i": "🧵", "c": "rukodelie-i-diy"}, {"s": "skolko-shlevok-dolzhno-byt-na-zhenskikh-bryukakh", "t": "Сколько шлёвок должно быть на женских брюках: нормы и виды", "i": "🩳", "c": "bryuki-i-shorty"}, {"s": "skolko-zvezd-u-podpolkovnika-na-pogonakh-v-politsii", "t": "Сколько звезд у подполковника полиции: фото и правила ношения", "i": "🪖", "c": "voennaya-forma"}, {"s": "skhema-vyazaniya-kapyushona-spitsami", "t": "Схема вязания капюшона спицами: расчет, убавки и модели", "i": "🧵", "c": "rukodelie-i-diy"}, {"s": "skhema-kryuchkom-shapka", "t": "Схема крючком шапка: подробный мастер-класс", "i": "🧵", "c": "rukodelie-i-diy"}, {"s": "skhema-palantina-kryuchkom-s-opisaniem-i-skhemami", "t": "Схема палантина крючком: описание, схемы и советы", "i": "🧣", "c": "sharfy-i-platki"}, {"s": "skhema-sharfa-kryuchkom-dlya-nachinayushchikh", "t": "Схема шарфа крючком для начинающих: пошаговая инструкция", "i": "🧵", "c": "rukodelie-i-diy"}, {"s": "skhemy-vyazaniya-kryuchkom-koftochek", "t": "Схемы вязания крючком кофточек: от простых до сложных моделей", "i": "🧵", "c": "rukodelie-i-diy"}, {"s": "skolko-nuzhno-fatina-na-yubku-dlya-zhenshchiny", "t": "Сколько нужно фатина на юбку: точный расчет метража", "i": "👚", "c": "yubki"}, {"s": "skhema-baktusa-spitsami", "t": "Схема бактуса спицами: пошаговое вязание и узоры", "i": "🧣", "c": "sharfy-i-platki"}, {"s": "skhema-vorotnichka-kryuchkom-k-platyu", "t": "Схема воротничка крючком к платью: мастер-класс и узоры", "i": "🧵", "c": "rukodelie-i-diy"}, {"s": "skhema-vyazaniya-kosynki", "t": "Схема вязания косынки: пошаговая инструкция и узоры", "i": "🧣", "c": "sharfy-i-platki"}, {"s": "skhema-vyazaniya-platya-dlya-kukly-kryuchkom", "t": "Схема вязания платья для куклы крючком: пошаговая инструкция", "i": "🧵", "c": "rukodelie-i-diy"}, {"s": "skhema-vyazaniya-shali-kryuchkom-s-ugla-s-opisaniem-dlya-nachinayushchikh", "t": "Схема вязания шали с угла: пошаговое описание для новичков", "i": "🧣", "c": "sharfy-i-platki"}, {"s": "skinni-na-muzhchinakh", "t": "Скинни на мужчинах: как носить, сочетать и кому идут", "i": "🩳", "c": "bryuki-i-shorty"}, {"s": "skhema-obrabotki-potajnoj-molnii", "t": "Схема обработки потайной молнии: пошаговая инструкция", "i": "🧵", "c": "rukodelie-i-diy"}, {"s": "skhema-vyazaniya-lifa-kryuchkom", "t": "Схема вязания лифа крючком: пошаговая инструкция для начинающих", "i": "🧵", "c": "rukodelie-i-diy"}, {"s": "skhemy-vyazaniya-kryuchkom-sharfov", "t": "Схемы вязания крючком шарфов: лучшие узоры и пошаговые инструкции", "i": "🧣", "c": "sharfy-i-platki"}, {"s": "skolko-tkani-nuzhno-na-yubku-karandash", "t": "Расход ткани на юбку-карандаш: точный расчет для любой фигуры", "i": "👚", "c": "yubki"}, {"s": "skolko-vesit-snaryazhenie-pozharnogo", "t": "Сколько весит снаряжение пожарного: вес комплекта", "i": "🦺", "c": "spetsodezhda"}, {"s": "skhemy-vyazaniya-noskov-spitsami", "t": "Схемы вязания носков спицами: пошаговые инструкции", "i": "🧵", "c": "rukodelie-i-diy"}, {"s": "skolko-zvezd-u-polkovnika-na-pogonakh-kartinki", "t": "Сколько звезд у полковника на погонах: фото и описание", "i": "🪖", "c": "voennaya-forma"}, {"s": "skhema-kosynki-kryuchkom", "t": "Схема косынки крючком: пошаговая инструкция для начинающих", "i": "🧣", "c": "sharfy-i-platki"}, {"s": "skhema-vyazaniya-shapki-s-ushkami-spitsami-dlya-devochki", "t": "Схема вязания шапки с ушками спицами для девочки: пошагово", "i": "🧵", "c": "rukodelie-i-diy"}, {"s": "skhema-vyazaniya-snuda-spitsami-s-opisaniem", "t": "Схема вязания снуда спицами: описание и узоры", "i": "🧣", "c": "sharfy-i-platki"}, {"s": "skhema-vyazaniya-svitera-oversajz", "t": "Схема вязания свитера оверсайз: выкройка, расчеты, спицы", "i": "🧵", "c": "rukodelie-i-diy"}, {"s": "skolko-tkani-nado-na-yubku-solntse", "t": "Расход ткани на юбку солнце: точный расчет по размерам", "i": "👚", "c": "yubki"}, {"s": "skolko-vremeni-kipyatit-bele", "t": "Сколько времени кипятить белье: тайминг для разных тканей", "i": "🧼", "c": "ukhod-za-odezhdoj"}, {"s": "skolko-zvezd-na-pogonakh-u-mladshego-lejtenanta", "t": "Сколько звезд на погонах у младшего лейтенанта: описание знаков", "i": "🪖", "c": "voennaya-forma"}, {"s": "skladka-na-yubke-kak-nazyvaetsya", "t": "Как называется складка на юбке: полный гид по видам драпировки", "i": "👚", "c": "yubki"}, {"s": "skhema-vyazaniya-detskogo-kombinezona-spitsami-6-9-mesyatsev-skhemy-i-opisanie", "t": "Вязаный комбинезон 6-9 месяцев спицами: схемы и описание", "i": "🧵", "c": "rukodelie-i-diy"}, {"s": "skhemy-dlya-vyazaniya-shali-kryuchkom", "t": "Схемы для вязания шали крючком: узоры и инструкции", "i": "🧵", "c": "rukodelie-i-diy"}, {"s": "skhema-vyazaniya-galstuka", "t": "Схема вязания галстука крючком: пошаговый мастер-класс", "i": "👜", "c": "aksessuary"}, {"s": "skhemy-vyazaniya-kardigana-kryuchkom", "t": "Схемы вязания кардигана крючком: пошаговые инструкции", "i": "🧵", "c": "rukodelie-i-diy"}, {"s": "skhemy-vyazaniya-kryuchkom-koftochek-dlya-zhenshchin", "t": "Схемы вязания крючком кофточек для женщин: подборка и советы", "i": "🧵", "c": "rukodelie-i-diy"}, {"s": "skolko-den-v-kapronovykh-kolgotkakh", "t": "Сколько дней носить капроновые колготки: нормы гигиены и долговечность", "i": "👙", "c": "nizhnee-belyo-i-kolgotki"}, {"s": "skolko-zvezd-u-majora-na-pogonakh-v-politsii", "t": "Сколько звезд у майора полиции: знаки различия на погонах", "i": "🪖", "c": "voennaya-forma"}, {"s": "skhema-chepchika-kryuchkom", "t": "Схема чепчика крючком: пошаговая инструкция для новорожденных", "i": "🧵", "c": "rukodelie-i-diy"}, {"s": "skhema-top-kryuchkom", "t": "Схема топ крючком: пошаговая инструкция и видео-уроки", "i": "🧵", "c": "rukodelie-i-diy"}, {"s": "skhema-yubki-kryuchkom-dlya-devochki", "t": "Схема юбки крючком для девочки: пошаговая инструкция", "i": "🧵", "c": "rukodelie-i-diy"}, {"s": "skhemy-kryuchkom-dlya-kofty", "t": "Схемы крючком для кофты: узоры, выкройки и пошаговый мастер-класс", "i": "🧵", "c": "rukodelie-i-diy"}, {"s": "skhemy-vyazaniya-dlya-devochek", "t": "Схемы вязания для девочек: ажурные кофты и платья", "i": "🧵", "c": "rukodelie-i-diy"}, {"s": "skinni-na-parnyakh", "t": "Скинни на парнях: кому идут, как носить и сочетать", "i": "👖", "c": "dzhinsy"}, {"s": "skolko-nuzhno-nabrat-petel-dlya-sharfa", "t": "Сколько нужно набрать петель для шарфа: точный расчет", "i": "🧣", "c": "sharfy-i-platki"}, {"s": "skolko-nuzhno-tkani-dlya-yubki-polusolntse", "t": "Расход ткани на юбку полусолнце: калькулятор и советы", "i": "🧵", "c": "rukodelie-i-diy"}, {"s": "skolko-pryazhi-nuzhno-na-snud", "t": "Сколько пряжи нужно на снуд: расчет по размерам и плотности", "i": "🧵", "c": "rukodelie-i-diy"}, {"s": "skhema-vyazaniya-kryuchkom-azhurnogo-vorotnika", "t": "Схема вязания крючком ажурного воротника: пошаговый урок", "i": "🧵", "c": "rukodelie-i-diy"}, {"s": "skhema-vyazaniya-svitera-oversajz-spitsami-dlya-zhenshchin", "t": "Схема вязания свитера оверсайз спицами для женщин: пошагово", "i": "📁", "c": null}, {"s": "skhema-zhileta-kryuchkom", "t": "Схема жилета крючком: пошаговый мастер-класс для начинающих", "i": "🧵", "c": "rukodelie-i-diy"}, {"s": "skhema-bolero-kryuchkom-dlya-zhenshchin", "t": "Схема болеро крючком для женщин: схемы, выкройки и вязание", "i": "🧵", "c": "rukodelie-i-diy"}, {"s": "skhema-kak-zavyazat-galstuk-muzhskoj", "t": "Схема как завязать галстук мужской: 5 способов пошагово", "i": "👜", "c": "aksessuary"}, {"s": "skhema-obrabotki-vorotnika-stojki", "t": "Схема обработки воротника-стойки: пошаговая инструкция", "i": "🧵", "c": "rukodelie-i-diy"}, {"s": "skhema-svitera-oversajz-spitsami", "t": "Схема свитера оверсайз спицами: вязание, выкройки, секреты", "i": "🧵", "c": "rukodelie-i-diy"}, {"s": "skhema-vorotnika-kryuchkom-na-plate-s-opisaniem-i-skhemami", "t": "Схема воротника крючком на платье: узоры и описание", "i": "🧵", "c": "rukodelie-i-diy"}, {"s": "skhema-vyazanykh-yubok", "t": "Схема вязаных юбок: от простых узоров до сложных техник", "i": "🧵", "c": "rukodelie-i-diy"}, {"s": "skhema-zavyazki-galstuka-muzhskogo", "t": "Схема завязки галстука: 3 классических узла для мужчин", "i": "👜", "c": "aksessuary"}, {"s": "skolko-den-byvayut-kolgotki-zhenskie-kapronovye", "t": "Сколько ден бывают колготки женские капроновые: таблица плотности", "i": "👙", "c": "nizhnee-belyo-i-kolgotki"}, {"s": "skhema-babochki-iz-bisera-dlya-nachinayushchikh", "t": "Схема бабочки из бисера для начинающих: пошаговая инструкция", "i": "🧵", "c": "rukodelie-i-diy"}, {"s": "skhema-kak-zavyazat-bantik", "t": "Схема как завязать бантик: 10 способов для разных случаев", "i": "👜", "c": "aksessuary"}, {"s": "skhema-kokoshnika-iz-kartona-raspechatat", "t": "Схема кокошника из картона: шаблоны, выкройки и мастер-класс", "i": "👘", "c": "natsionalnaya-i-istoricheskaya-odezhda"}, {"s": "skhema-pleteniya-babochki-iz-bisera-dlya-nachinayushchikh", "t": "Схема плетения бабочки из бисера: мастер-класс для новичков", "i": "🧵", "c": "rukodelie-i-diy"}, {"s": "skhema-vorotnichkov-kryuchkom", "t": "Схема воротничков крючком: узоры, выкройки и пошаговое вязание", "i": "🧵", "c": "rukodelie-i-diy"}, {"s": "skhema-vyazaniya-baktusa-kryuchkom-s-opisaniem", "t": "Схема вязания бактуса крючком: описание и узоры", "i": "🧵", "c": "rukodelie-i-diy"}, {"s": "skhema-vyazaniya-kryuchkom-topa-dlya-devushki", "t": "Схема вязания топа крючком: пошаговая инструкция", "i": "🧵", "c": "rukodelie-i-diy"}, {"s": "skhemy-dlya-baktusa-kryuchkom", "t": "Схемы для бактуса крючком: пошаговые инструкции и узоры", "i": "🧵", "c": "rukodelie-i-diy"}, {"s": "skhema-kryuchkom-shal", "t": "Схема крючком шаль: пошаговая инструкция и узоры", "i": "🧵", "c": "rukodelie-i-diy"}, {"s": "skhema-vyazaniya-baktusa-spitsami", "t": "Схема вязания бактуса спицами: пошаговая инструкция", "i": "🧵", "c": "rukodelie-i-diy"}, {"s": "skhema-vyazaniya-shapochki-kryuchkom", "t": "Схема вязания шапочки крючком: пошаговый мастер-класс", "i": "🧵", "c": "rukodelie-i-diy"}, {"s": "skinni-dzhinsy-muzhskie-s-chem-nosit", "t": "Мужские скинни: с чем носить, сочетания и правила стиля", "i": "👖", "c": "dzhinsy"}, {"s": "skolko-zvezd-na-pogonakh-generala", "t": "Сколько звезд на погонах генерала: таблица по родам войск", "i": "🪖", "c": "voennaya-forma"}, {"s": "skolko-zvezd-na-pogonakh-podpolkovnika", "t": "Звезды подполковника: количество, размер и правила ношения", "i": "🪖", "c": "voennaya-forma"}, {"s": "skolko-zvezd-na-pogonakh-u-generala-lejtenanta", "t": "Звезды на погонах генерал-лейтенанта: количество и порядок ношения", "i": "🪖", "c": "voennaya-forma"}, {"s": "skhema-vyazaniya-kryuchkom-kosynki-dlya-zhenshchin", "t": "Схема вязания косынки крючком: пошаговый мастер-класс", "i": "🧵", "c": "rukodelie-i-diy"}, {"s": "skhema-vyazaniya-vorotnika", "t": "Схема вязания воротника: пошаговые инструкции и узоры", "i": "🧵", "c": "rukodelie-i-diy"}, {"s": "skinni-dzhinsy-vikipediya", "t": "Скинни джинсы: история, фасоны, с чем носить", "i": "👖", "c": "dzhinsy"}, {"s": "skolko-zvezd-u-kapitana-politsii-na-pogonakh", "t": "Звезды на погонах полиции: расшифровка званий и правила ношения", "i": "🪖", "c": "voennaya-forma"}, {"s": "skolko-zvezdochek-u-mladshego-lejtenanta", "t": "Сколько звездочек у младшего лейтенанта: знаки различия", "i": "🪖", "c": "voennaya-forma"}, {"s": "skhema-pleteniya-laptej-dlya-nachinayushchikh-poshagovo", "t": "Схема плетения лаптей для начинающих пошагово: инструкция", "i": "👘", "c": "natsionalnaya-i-istoricheskaya-odezhda"}, {"s": "skhema-zavyazyvaniya-galstukov", "t": "Схема завязывания галстуков: пошаговые инструкции для всех типов", "i": "👜", "c": "aksessuary"}, {"s": "skolko-sm-pogony", "t": "Размеры погон по ГОСТ: таблица длины и ширины", "i": "🪖", "c": "voennaya-forma"}, {"s": "skolko-zvezd-u-polkovnika-mvd", "t": "Сколько звезд у полковника МВД: погоны, знаки и форма", "i": "🪖", "c": "voennaya-forma"}, {"s": "skhema-skladyvaniya-futbolki", "t": "Схема складывания футболки: методы для идеального порядка", "i": "👕", "c": "futbolki-i-topy"}, {"s": "skhema-dlya-kofty-kryuchkom", "t": "Схема для кофты крючком: пошаговый мастер-класс", "i": "🧵", "c": "rukodelie-i-diy"}, {"s": "skhema-dlya-shali-kryuchkom", "t": "Схема для шали крючком: узоры, инструкции и описание", "i": "🧵", "c": "rukodelie-i-diy"}, {"s": "skhema-vyazaniya-kofty-spitsami-dlya-zhenshchin", "t": "Схема вязания кофты спицами для женщин: подробный разбор", "i": "🧵", "c": "rukodelie-i-diy"}, {"s": "skhema-yubki-kryuchkom-dlya-zhenshchin-s-rasshireniem-k-nizu", "t": "Схема юбки крючком для женщин: расширение к низу", "i": "🧵", "c": "rukodelie-i-diy"}, {"s": "skinni-dzhinsy-porvannye", "t": "Скинни джинсы порванные: как носить, сочетать и ремонтировать", "i": "👖", "c": "dzhinsy"}, {"s": "skolko-zvezdochek-u-majora-na-pogonakh", "t": "Сколько звездочек у майора на погонах: знаки различия РФ", "i": "🪖", "c": "voennaya-forma"}, {"s": "skhema-baktusa-kryuchkom-s-opisaniem-i-skhemami", "t": "Схема бактуса крючком: описание, узоры и советы по вязанию", "i": "🧣", "c": "sharfy-i-platki"}, {"s": "skhema-baktusa-kryuchkom-s-opisaniem", "t": "Схема бактуса крючком: пошаговое описание и советы", "i": "🧣", "c": "sharfy-i-platki"}, {"s": "skhema-bantika-kryuchkom", "t": "Схема бантика крючком: пошаговая инструкция и 3 варианта", "i": "🧵", "c": "rukodelie-i-diy"}, {"s": "skhema-zavyazat-galstuk-muzhskoj-klassicheskij-kak-poshagovo", "t": "Как завязать классический галстук: пошаговая схема для мужчин", "i": "👜", "c": "aksessuary"}, {"s": "skhemy-vyazaniya-kryuchkom-kofty", "t": "Схемы вязания крючком кофты: пошаговый мастер-класс", "i": "🧵", "c": "rukodelie-i-diy"}, {"s": "skladyvalka-dlya-futbolok", "t": "Складывалка для футболок: виды, выбор и как сложить за 2 сек", "i": "🧼", "c": "ukhod-za-odezhdoj"}, {"s": "skolko-u-kapitana-zvezd-na-pogonakh", "t": "Сколько у капитана звезд на погонах: знаки различия в ВС РФ", "i": "🪖", "c": "voennaya-forma"}, {"s": "skhema-palantina-kryuchkom", "t": "Схема палантина крючком: пошаговые узоры и советы", "i": "🧣", "c": "sharfy-i-platki"}, {"s": "skhema-povyazki-na-golovu-kryuchkom", "t": "Схема повязки на голову крючком: мастер-класс и советы", "i": "🧵", "c": "rukodelie-i-diy"}, {"s": "skhemy-azhurnoj-vyazki", "t": "Схемы ажурной вязки: узоры спицами и крючком для начинающих", "i": "🧵", "c": "rukodelie-i-diy"}, {"s": "skinni-dzhinsy-muzhchiny", "t": "Мужские скинни джинсы: как выбрать и с чем носить", "i": "👖", "c": "dzhinsy"}, {"s": "skolko-sushchestvuet-sposobov-zavyazat-galstuk", "t": "Способы завязать галстук: полная энциклопедия узлов", "i": "👜", "c": "aksessuary"}, {"s": "skhema-shapki-kryuchkom", "t": "Схема шапки крючком: схемы и описание для начинающих", "i": "🧵", "c": "rukodelie-i-diy"}, {"s": "skhemy-koketok-kryuchkom", "t": "Схемы кокеток крючком: пошаговые инструкции и узоры", "i": "🧵", "c": "rukodelie-i-diy"}, {"s": "skhema-noski-kryuchkom", "t": "Схема носки крючком: пошаговая инструкция для начинающих", "i": "🧵", "c": "rukodelie-i-diy"}, {"s": "skhema-vyazaniya-sharfa-spitsami-dlya-nachinayushchikh", "t": "Схема вязания шарфа спицами для начинающих: пошаговый урок", "i": "🧣", "c": "sharfy-i-platki"}, {"s": "skhema-vyazaniya-topa-kryuchkom-dlya-devushek", "t": "Схема вязания топа крючком для девушек: пошаговый мастер-класс", "i": "🧵", "c": "rukodelie-i-diy"}, {"s": "skhemy-kryuchkom-dlya-yubki", "t": "Схемы крючком для юбки: лучшие модели и инструкции", "i": "🧵", "c": "rukodelie-i-diy"}, {"s": "skhemy-shnurovki-botinok", "t": "Схемы шнуровки ботинок: лучшие способы и инструкции", "i": "👟", "c": "obuv"}, {"s": "skhema-vyazaniya-kryuchkom-vorotnichka", "t": "Схема вязания крючком воротничка: пошаговый мастер-класс", "i": "🧵", "c": "rukodelie-i-diy"}, {"s": "skhema-vyazaniya-spitsami-svitera-zhenskogo-dlya-nachinayushchikh", "t": "Схема вязания свитера спицами для начинающих: пошаговый мастер-класс", "i": "🧵", "c": "rukodelie-i-diy"}, {"s": "skolko-zvezd-u-majora-na-pogonakh", "t": "Сколько звезд у майора: знаки различия на погонах", "i": "🪖", "c": "voennaya-forma"}, {"s": "skolko-zvezdochek-u-generala", "t": "Сколько звёздочек у генерала: знаки различия по званиям", "i": "🪖", "c": "voennaya-forma"}, {"s": "skhema-vyazaniya-povyazki-na-golovu-kryuchkom", "t": "Схема вязания повязки на голову крючком: пошаговый мастер-класс", "i": "🧵", "c": "rukodelie-i-diy"}, {"s": "skhema-vyazaniya-spitsami-svitera-zhenskogo-oversajz", "t": "Схема вязания свитера оверсайз спицами: пошаговая инструкция", "i": "📁", "c": null}, {"s": "skhemy-kruglykh-koketok-kryuchkom", "t": "Схемы круглых кокеток крючком: расчеты и узоры", "i": "🧵", "c": "rukodelie-i-diy"}, {"s": "skhemy-vyazaniya-baktusa-spitsami", "t": "Схемы вязания бактуса спицами: узоры и мастер-классы", "i": "🧵", "c": "rukodelie-i-diy"}, {"s": "skhemy-vyazaniya-kryuchkom-sharfa", "t": "Схемы вязания крючком шарфа: узоры для начинающих", "i": "🧵", "c": "rukodelie-i-diy"}, {"s": "skinni-dzhinsy-muzhskie-eto", "t": "Скинни джинсы мужские: что это, кому идут и с чем носить", "i": "👖", "c": "dzhinsy"}, {"s": "skladka-na-yubke", "t": "Складка на юбке: виды, названия и как сделать", "i": "👚", "c": "yubki"}, {"s": "skromnye-svadebnye-platya", "t": "Скромные свадебные платья: фасоны, ткани и советы", "i": "👗", "c": "platya-i-sarafany"}, {"s": "skhema-kardigana-iz-kvadratov", "t": "Схема кардигана из квадратов: вязание и сборка", "i": "🧵", "c": "rukodelie-i-diy"}, {"s": "skhema-vyazaniya-baktusa-spitsami-s-opisaniem", "t": "Схема вязания бактуса спицами: пошаговое описание", "i": "🧵", "c": "rukodelie-i-diy"}, {"s": "skhema-vyazaniya-futbolki-spitsami", "t": "Схема вязания футболки спицами: пошаговый мастер-класс", "i": "🧵", "c": "rukodelie-i-diy"}, {"s": "skhema-vyazaniya-konverta-dlya-novorozhdennogo-spitsami", "t": "Схема вязания конверта для новорожденного спицами: пошагово", "i": "🧵", "c": "rukodelie-i-diy"}, {"s": "skhemy-kryuchkom-dlya-shali", "t": "Схемы крючком для шали: пошаговые инструкции и узоры", "i": "🧣", "c": "sharfy-i-platki"}, {"s": "skhemy-vyazaniya-kryuchkom-shalej", "t": "Схемы вязания шалей крючком: от простых до ажурных", "i": "🧵", "c": "rukodelie-i-diy"}, {"s": "skhemy-vyazaniya-shali-kryuchkom-s-opisaniem", "t": "Схемы вязания шали крючком: 5 лучших узоров с описанием", "i": "🧵", "c": "rukodelie-i-diy"}, {"s": "skinni-i-slim-v-chem-raznitsa", "t": "Скинни и слим в чем разница: как выбрать идеальные брюки", "i": "🩳", "c": "bryuki-i-shorty"}, {"s": "skinni-bryuki-muzhskie", "t": "Мужские скинни брюки: как выбрать и с чем носить", "i": "🩳", "c": "bryuki-i-shorty"}, {"s": "skhema-kofty-spitsami", "t": "Схема кофты спицами: пошаговая инструкция для начинающих", "i": "🧵", "c": "rukodelie-i-diy"}, {"s": "skhema-vyazaniya-kryuchkom-kofty", "t": "Схема вязания кофты крючком: пошаговая инструкция и советы", "i": "🧵", "c": "rukodelie-i-diy"}, {"s": "skhema-dlya-bisera-babochka", "t": "Схемы для бисера бабочка: пошаговые инструкции", "i": "🧵", "c": "rukodelie-i-diy"}, {"s": "skhemy-vyazaniya-kryuchkom-odezhdy-dlya-kukol", "t": "Схемы вязания крючком одежды для кукол: мастер-класс", "i": "🧵", "c": "rukodelie-i-diy"}, {"s": "skolko-kipyatyat-bele", "t": "Сколько кипятят белье: время для разных тканей и пятен", "i": "🧼", "c": "ukhod-za-odezhdoj"}, {"s": "skolko-tkani-nado-na-futbolku", "t": "Сколько ткани нужно на футболку: расчеты, нормы расхода и виды материала", "i": "👕", "c": "futbolki-i-topy"}, {"s": "skolko-vremeni-nuzhno-chtoby-svyazat-sviter", "t": "Сколько времени нужно чтобы связать свитер: расчет часов по плотности", "i": "📁", "c": null}, {"s": "skolko-zvezd-mladshij-lejtenant", "t": "Сколько звезд у младшего лейтенанта: погоны, знаки различия и форма", "i": "🪖", "c": "voennaya-forma"}, {"s": "skolko-zvezd-u-serzhanta-na-pogonakh", "t": "Звезды на погонах сержанта: сколько, как носить и отличия", "i": "🪖", "c": "voennaya-forma"}, {"s": "skandinavskij-stil-odezhdy-dlya-zhenshchin", "t": "Скандинавский стиль одежды для женщин: гид по выбору и сочетаниям", "i": "👠", "c": "stil-i-moda"}, {"s": "skhema-krugloj-koketki-kryuchkom", "t": "Схема круглой кокетки крючком: пошаговый расчет и вязание", "i": "🧵", "c": "rukodelie-i-diy"}, {"s": "skhema-vyazaniya-kryuchkom-svitera-oversajz", "t": "Схема вязания крючком свитера оверсайз: подробный мастер-класс", "i": "📁", "c": null}, {"s": "skhema-vyazaniya-shlyapki-kryuchkom-dlya-zhenshchin", "t": "Схема вязания шляпки крючком: пошаговый мастер-класс", "i": "🧵", "c": "rukodelie-i-diy"}, {"s": "skhemy-shalej-kryuchkom-s-ugla", "t": "Схемы шалей крючком с угла: пошаговые инструкции", "i": "🧵", "c": "rukodelie-i-diy"}, {"s": "skhemy-uzorov-kryuchkom-dlya-koftochek", "t": "Схемы узоров крючком для кофточек: от ажурных до плотных", "i": "🧵", "c": "rukodelie-i-diy"}, {"s": "skhemy-vyazaniya-svitera-kryuchkom", "t": "Схемы вязания свитера крючком: от выбора узора до сборки", "i": "📁", "c": null}, {"s": "skin-tsvet-kakoj", "t": "Skin цвет какой: оттенки и сочетания в одежде", "i": "👠", "c": "stil-i-moda"}, {"s": "skolko-zvezd-na-pogonakh-u-praporshchika", "t": "Сколько звезд на погонах у прапорщика: знаки различия РФ", "i": "🪖", "c": "voennaya-forma"}, {"s": "skhemy-vyazaniya-spitsami-koftochek-dlya-zhenshchin-s-opisaniem-i-skhemami-besplatno", "t": "Схемы вязания спицами кофточек для женщин с описанием бесплатно", "i": "🧶", "c": "kofty-i-svitery"}, {"s": "skhema-vyazaniya-kryuchkom-kardigana", "t": "Схема вязания кардигана крючком: от мерок до сборки", "i": "🧵", "c": "rukodelie-i-diy"}, {"s": "skhema-vyazaniya-noskov-na-2-spitsakh", "t": "Схема вязания носков на 2 спицах: мастер-класс для начинающих", "i": "🧵", "c": "rukodelie-i-diy"}, {"s": "skhema-vyazaniya-povyazki-na-golovu", "t": "Схема вязания повязки на голову: спицы и крючок", "i": "🧵", "c": "rukodelie-i-diy"}, {"s": "skhema-yubki-kryuchkom", "t": "Схема юбки крючком: как связать, выбрать фасон и пряжу", "i": "🧵", "c": "rukodelie-i-diy"}, {"s": "skhema-zavyazat-galstuk-muzhskoj-klassicheskij", "t": "Как завязать классический галстук: схема пошагово", "i": "👜", "c": "aksessuary"}, {"s": "skhemy-dlya-vyazaniya-kryuchkom-kardigan", "t": "Схемы для вязания крючком кардиган: лучшие модели и инструкции", "i": "🧵", "c": "rukodelie-i-diy"}, {"s": "skhemy-krugloj-koketki-kryuchkom", "t": "Схемы круглой кокетки крючком: расчет и вязание", "i": "🧵", "c": "rukodelie-i-diy"}, {"s": "skhema-vyazaniya-kofty", "t": "Схема вязания кофты: пошаговая инструкция для начинающих", "i": "🧵", "c": "rukodelie-i-diy"}, {"s": "skhema-vyazaniya-kryuchkom-kardigan", "t": "Схема вязания крючком кардиган: подробный мастер-класс", "i": "🧵", "c": "rukodelie-i-diy"}, {"s": "skhema-kardigan-spitsami", "t": "Схема кардиган спицами: пошаговая инструкция, выкройки и фасоны", "i": "🧵", "c": "rukodelie-i-diy"}, {"s": "skhema-panamki-kryuchkom", "t": "Схема панамки крючком: пошаговая инструкция и расчет", "i": "🧵", "c": "rukodelie-i-diy"}, {"s": "skhema-vyazaniya-topa", "t": "Схема вязания топа: пошаговые инструкции и узоры", "i": "🧵", "c": "rukodelie-i-diy"}, {"s": "skhemy-vyazaniya-spitsami-azhurnykh-uzorov-dlya-palantina", "t": "Схемы вязания спицами ажурных узоров для палантина: 10+ вариантов", "i": "🧣", "c": "sharfy-i-platki"}, {"s": "skhema-kosynki-kryuchkom-dlya-zhenshchin-s-opisaniem-i-skhemami", "t": "Схема косынки крючком для женщин: описание, схемы и модели", "i": "🧣", "c": "sharfy-i-platki"}, {"s": "skhema-vyazaniya-kryuchkom-kosynki", "t": "Схема вязания косынки крючком: пошаговая инструкция и узоры", "i": "🧵", "c": "rukodelie-i-diy"}, {"s": "skolko-kipyatit-bele-dlya-otbelivaniya-s-poroshkom", "t": "Сколько кипятить белье для отбеливания с порошком: время и правила", "i": "🧼", "c": "ukhod-za-odezhdoj"}, {"s": "skhema-kosynki-kryuchkom-dlya-zhenshchin", "t": "Схема косынки крючком для женщин: пошаговый мастер-класс", "i": "🧣", "c": "sharfy-i-platki"}, {"s": "skhema-razmeshcheniya-znakov-razlichiya-na-voennoj-forme-novogo-obraztsa", "t": "Схема знаков различия на военной форме: правила ношения", "i": "🪖", "c": "voennaya-forma"}, {"s": "skhema-vyazaniya-bereta-spitsami", "t": "Схема вязания берета спицами: пошаговая инструкция", "i": "🧵", "c": "rukodelie-i-diy"}, {"s": "skladyvaem-futbolki-pravilno", "t": "Как правильно складывать футболки: 5 методов хранения", "i": "🧼", "c": "ukhod-za-odezhdoj"}, {"s": "skhema-koketki-kryuchkom-dlya-zhenskogo-platya", "t": "Схема кокетки крючком: как связать женское платье", "i": "🧵", "c": "rukodelie-i-diy"}, {"s": "skhema-vyazaniya-kryuchkom-sharfa", "t": "Схема вязания шарфа крючком: от узоров до сборки", "i": "🧵", "c": "rukodelie-i-diy"}, {"s": "skhema-zavyazyvaniya-pionerskogo-galstuka", "t": "Схема завязывания пионерского галстука: пошаговая инструкция", "i": "👜", "c": "aksessuary"}, {"s": "skhemy-vyazaniya-kryuchkom-dlya-nachinayushchikh-samye-prostye-s-opisaniem-dlya-koftochek", "t": "Простые схемы вязания крючком кофточек для начинающих", "i": "🧶", "c": "kofty-i-svitery"}, {"s": "skolko-zvezd-na-pogonakh", "t": "Сколько звезд на погонах: таблица званий и расшифровка", "i": "🪖", "c": "voennaya-forma"}, {"s": "skolko-zvezdochek-u-polkovnika", "t": "Сколько звездочек у полковника: погоны РФ и СССР", "i": "🪖", "c": "voennaya-forma"}, {"s": "skolko-medalej-veshaetsya-v-odin-ryad-na-paradnoj-forme", "t": "Сколько медалей в ряд на парадной форме: нормы и правила ношения", "i": "🪖", "c": "voennaya-forma"}, {"s": "skhema-baktusa-spitsami-s-opisaniem-i-skhemami", "t": "Схема бактуса спицами: 5 лучших моделей с описанием", "i": "🧣", "c": "sharfy-i-platki"}, {"s": "skhema-zhiletki-kryuchkom", "t": "Схема жилетки крючком: пошаговый мастер-класс для начинающих", "i": "🧵", "c": "rukodelie-i-diy"}, {"s": "skolko-nuzhno-kipyatit-bele", "t": "Сколько нужно кипятить белье: время, температура, правила", "i": "🧼", "c": "ukhod-za-odezhdoj"}, {"s": "skhema-pleteniya-laptej", "t": "Схема плетения лаптей: пошаговая инструкция", "i": "👘", "c": "natsionalnaya-i-istoricheskaya-odezhda"}, {"s": "skhema-zavyazyvaniya-bantika-iz-lenty", "t": "Схема завязывания бантика из ленты: пошаговые инструкции", "i": "🧵", "c": "rukodelie-i-diy"}, {"s": "skhemy-shalej-kryuchkom-novye-modeli-besplatno", "t": "Схемы шалей крючком: новые модели бесплатно", "i": "🧣", "c": "sharfy-i-platki"}, {"s": "skhemy-shali-kryuchkom-prostye-no-krasivye-skhemy-s-ugla", "t": "Схемы шали крючком простые но красивые с угла: мастер-класс", "i": "🧣", "c": "sharfy-i-platki"}, {"s": "skolko-zvezdochek-u-lejtenanta", "t": "Сколько звездочек у лейтенанта: знаки различия и правила", "i": "🪖", "c": "voennaya-forma"}, {"s": "skolko-zvezdochek-u-starshego-lejtenanta", "t": "Звездочки старшего лейтенанта: расположение на погонах", "i": "🪖", "c": "voennaya-forma"}, {"s": "skandi-stil-odezhdy", "t": "Сканди стиль в одежде: как создать скандинавский гардероб", "i": "👠", "c": "stil-i-moda"}, {"s": "skhema-vyazaniya-palantina-spitsami-azhurnym-uzorom", "t": "Схема вязания палантина спицами: ажурный узор для начинающих", "i": "🧵", "c": "rukodelie-i-diy"}, {"s": "skhemy-vyazaniya-kryuchkom-kardiganov", "t": "Схемы вязания крючком кардиганов: выбор, фасоны, инструкции", "i": "🧵", "c": "rukodelie-i-diy"}, {"s": "skinny-jeans-muzhskie", "t": "Мужские Skinny Jeans: С чем носить, как выбрать и ушить", "i": "👖", "c": "dzhinsy"}, {"s": "skladki-na-bryukakh", "t": "Складки на брюках: как заутюжить, отпарить и сохранить стрелки", "i": "🩳", "c": "bryuki-i-shorty"}, {"s": "skolko-petel-nabirat-na-noski", "t": "Сколько петель набирать на носки: расчёт по таблице", "i": "🧵", "c": "rukodelie-i-diy"}, {"s": "skolko-poslerodovykh-trusov-nuzhno", "t": "Сколько послеродовых трусов нужно: расчеты и советы", "i": "👙", "c": "nizhnee-belyo-i-kolgotki"}, {"s": "skolko-zvezd-u-generala-armii", "t": "Сколько звезд у генерала армии: знаки различия и форма", "i": "🪖", "c": "voennaya-forma"}, {"s": "skromnoe-plate-na-svadbu-dlya-nevesty", "t": "Скромное платье на свадьбу: фасоны для невесты", "i": "👗", "c": "platya-i-sarafany"}, {"s": "skhema-dlya-kardigana-kryuchkom", "t": "Схема для кардигана крючком: пошаговые инструкции", "i": "🧵", "c": "rukodelie-i-diy"}, {"s": "skhema-bantika-iz-lenty", "t": "Схема бантика из ленты: пошаговые мастер-классы для новичков", "i": "🧵", "c": "rukodelie-i-diy"}, {"s": "skhema-vyazaniya-yubki-kryuchkom", "t": "Схема вязания юбки крючком: пошаговая инструкция и узоры", "i": "🧵", "c": "rukodelie-i-diy"}, {"s": "skhemy-shalej-kryuchkom", "t": "Схемы шалей крючком: лучшие узоры для начинающих", "i": "🧵", "c": "rukodelie-i-diy"}, {"s": "skhemy-vyazaniya-kryuchkom-kardiganov-dlya-zhenshchin-modnye-s-opisaniem-i-skhemami", "t": "Схемы вязания крючком кардиганов для женщин: модные модели", "i": "🧵", "c": "rukodelie-i-diy"}, {"s": "skinny-i-slim-otlichie", "t": "Skinny и Slim: в чем разница и как выбрать идеальные джинсы", "i": "👖", "c": "dzhinsy"}, {"s": "skladyvanie-futbolki-odnim-dvizheniem", "t": "Как сложить футболку одним движением: мастер-класс", "i": "👕", "c": "futbolki-i-topy"}, {"s": "skolko-petel-nado-nabrat-dlya-noskov", "t": "Сколько петель набрать для носков: точный расчет по размеру", "i": "🧵", "c": "rukodelie-i-diy"}, {"s": "skolko-po-vremeni-nuzhno-kipyatit-belyo", "t": "Сколько по времени нужно кипятить белье: нормы и правила", "i": "🧼", "c": "ukhod-za-odezhdoj"}, {"s": "skolko-veshchej-dolzhno-byt-v-garderobe-zhenshchiny-50-let", "t": "Сколько вещей должно быть в гардеробе женщины 50 лет: формула стиля", "i": "👠", "c": "stil-i-moda"}, {"s": "skolko-zvezd-u-kapitana-politsii", "t": "Знаки различия капитана полиции РФ: звезды, погоны и форма", "i": "🪖", "c": "voennaya-forma"}, {"s": "skandinavskij-stil-odezhda", "t": "Скандинавский стиль в одежде: базовый гардероб и сочетания", "i": "👠", "c": "stil-i-moda"}, {"s": "skhema-babochka-kryuchkom", "t": "Схема бабочка крючком: пошаговый мастер-класс и описание", "i": "🧵", "c": "rukodelie-i-diy"}, {"s": "skhema-vyazaniya-bereta-kryuchkom-dlya-zhenshchin-s-opisaniem-i-skhemami-besplatno", "t": "Схема вязания берета крючком: описание и схемы бесплатно", "i": "🧵", "c": "rukodelie-i-diy"}, {"s": "skhema-vyazaniya-kombinezona-dlya-novorozhdennogo-spitsami-s-kapyushonom", "t": "Схема вязания комбинезона для новорожденного спицами с капюшоном", "i": "🧵", "c": "rukodelie-i-diy"}, {"s": "skhemy-azhurnykh-uzorov-kryuchkom-dlya-letnikh-koftochek", "t": "Ажурные кофточки крючком: схемы и узоры для лета", "i": "🧵", "c": "rukodelie-i-diy"}, {"s": "skolko-sm-mezhdu-zvezdami-na-pogonakh", "t": "Расстояние между звездами на погонах: нормы и правила ношения", "i": "🪖", "c": "voennaya-forma"}, {"s": "skolko-stoit-otparit-svadebnoe-plate", "t": "Сколько стоит отпарить свадебное платье: цены и нюансы ухода", "i": "🧼", "c": "ukhod-za-odezhdoj"}, {"s": "skhema-zavyazki-galstuka", "t": "Схема завязки галстука: 5 лучших узлов для мужчин", "i": "👜", "c": "aksessuary"}, {"s": "skhema-vyazaniya-kostyuma-dlya-novorozhdennogo-spitsami", "t": "Схема вязания костюма для новорожденного спицами: пошаговый мастер-класс", "i": "🧵", "c": "rukodelie-i-diy"}, {"s": "skhema-vyazaniya-topika-spitsami", "t": "Схема вязания топика спицами: пошаговая инструкция", "i": "🧵", "c": "rukodelie-i-diy"}, {"s": "skhemy-kak-zavyazat-galstuk", "t": "Схемы как завязать галстук: пошаговые инструкции для всех узлов", "i": "👜", "c": "aksessuary"}, {"s": "skhemy-vyazaniya-azhurnykh-uzorov-spitsami", "t": "Схемы вязания ажурных узоров спицами: инструкции и советы", "i": "🧵", "c": "rukodelie-i-diy"}, {"s": "skhemy-vyazaniya-kryuchkom-letnikh-koftochek-dlya-zhenshchin-s-opisaniem", "t": "Схемы вязания крючком летних кофточек: описание и модели", "i": "🧵", "c": "rukodelie-i-diy"}, {"s": "skolko-tkani-nuzhno-na-yubku-polusolntse", "t": "Сколько ткани нужно на юбку полусолнце: точный расчет расхода", "i": "👚", "c": "yubki"}, {"s": "skandinavskij-stil-odezhdy", "t": "Скандинавский стиль в одежде: особенности, гардероб и сочетания", "i": "👠", "c": "stil-i-moda"}, {"s": "skhema-vyazaniya-majki-kryuchkom", "t": "Схема вязания майки крючком: пошаговая инструкция", "i": "🧵", "c": "rukodelie-i-diy"}, {"s": "skhema-vyazaniya-panamki-kryuchkom", "t": "Схема вязания панамки крючком: пошаговая инструкция", "i": "🧵", "c": "rukodelie-i-diy"}, {"s": "skhema-dlya-vyazaniya-kryuchkom-shali", "t": "Схема для вязания крючком шали: лучшие узоры и инструкции", "i": "🧵", "c": "rukodelie-i-diy"}, {"s": "skhema-povyazki-na-golovu", "t": "Схема повязки на голову: пошаговые инструкции для новичков", "i": "🧵", "c": "rukodelie-i-diy"}, {"s": "skhema-azhurnoj-vyazki-spitsami", "t": "Схема ажурной вязки спицами: узоры, советы и инструкции", "i": "🧵", "c": "rukodelie-i-diy"}, {"s": "skhema-baktus-kryuchkom", "t": "Схема бактус крючком: пошаговая инструкция для начинающих", "i": "🧵", "c": "rukodelie-i-diy"}, {"s": "skhema-kofty-kryuchkom-dlya-zhenshchiny", "t": "Схема кофты крючком для женщины: подробный мастер-класс", "i": "🧵", "c": "rukodelie-i-diy"}, {"s": "skhema-vyazki-zhenskogo-kardigana-spitsami", "t": "Схема вязки женского кардигана спицами: пошаговый мастер-класс", "i": "🧵", "c": "rukodelie-i-diy"}, {"s": "skolko-let-diademu", "t": "Сколько лет диадему: как определить возраст украшения", "i": "👜", "c": "aksessuary"}, {"s": "skhema-svitera-oversajz", "t": "Схема свитера оверсайз: вязание, выкройки и советы", "i": "📁", "c": null}, {"s": "skhema-vyazaniya-kryuchkom-shal", "t": "Схема вязания крючком шаль: узоры, выбор пряжи и инструкции", "i": "🧵", "c": "rukodelie-i-diy"}, {"s": "skolko-nuzhno-pryazhi-dlya-noskov", "t": "Сколько нужно пряжи для носков: точный расчет", "i": "🧵", "c": "rukodelie-i-diy"}, {"s": "skolko-zvezd-u-marshala-na-pogonakh", "t": "Звезды на погонах маршала: количество, расположение и отличия", "i": "🪖", "c": "voennaya-forma"}, {"s": "skhemy-vyazaniya-shalej-kryuchkom-s-opisaniem-besplatno", "t": "Схемы вязания шалей крючком: бесплатные описания и узоры", "i": "🧵", "c": "rukodelie-i-diy"}, {"s": "skolko-petel-nado-nabirat-na-manishku", "t": "Сколько петель набирать на манишку: расчеты для спиц", "i": "🧵", "c": "rukodelie-i-diy"}, {"s": "skolko-zvezd-u-ofitsera", "t": "Сколько звезд у офицера: погоны, звания и правила ношения", "i": "🪖", "c": "voennaya-forma"}, {"s": "skhema-vyazaniya-kryuchkom-kardigana-dlya-zhenshchin", "t": "Схема вязания кардигана крючком: пошаговая инструкция", "i": "🧵", "c": "rukodelie-i-diy"}, {"s": "skhema-zavyazki-galstuka-klassicheskim-sposobom", "t": "Схема завязки галстука классическим способом: пошаговая инструкция", "i": "👜", "c": "aksessuary"}, {"s": "skinni-dzhinsy-muzhskie-chto-eto-znachit", "t": "Мужские скинни: что это значит и кому идет?", "i": "👖", "c": "dzhinsy"}, {"s": "skolko-nuzhno-fatina-na-pyshnuyu-yubku-dlya-zhenshchin", "t": "Сколько нужно фатина на пышную юбку: расчет расхода по фасонам", "i": "🧵", "c": "rukodelie-i-diy"}, {"s": "skhema-vyazki-kombinezona-dlya-novorozhdennogo", "t": "Схема вязки комбинезона для новорожденного спицами: пошагово", "i": "🧵", "c": "rukodelie-i-diy"}, {"s": "skhemy-vyazaniya-vorotnichkov-kryuchkom-s-opisaniem-i-skhemami", "t": "Схемы вязания воротничков крючком: 5 моделей с описанием", "i": "🧵", "c": "rukodelie-i-diy"}, {"s": "skladki-na-bryukakh-speredi-v-pakhu-kak-ubrat", "t": "Как убрать складки на брюках спереди: причины и решения", "i": "🩳", "c": "bryuki-i-shorty"}, {"s": "skladnaya-korzina-dlya-belya-svoimi-rukami", "t": "Складная корзина для белья своими руками: мастер-класс", "i": "🧵", "c": "rukodelie-i-diy"}, {"s": "skolzyashchij-uzel-dlya-shnurkov", "t": "Скользящий узел для шнурков: как завязать и затянуть", "i": "👜", "c": "aksessuary"}, {"s": "skhema-kryuchkom-yubka", "t": "Схема юбки крючком: схемы, узоры и пошаговая инструкция", "i": "🧵", "c": "rukodelie-i-diy"}, {"s": "skhema-vyazaniya-noski", "t": "Схема вязания носки: пошаговая инструкция для начинающих", "i": "🧵", "c": "rukodelie-i-diy"}, {"s": "skhema-vyazaniya-shapochki-dlya-novorozhdennogo-spitsami", "t": "Схема вязания шапочки для новорожденного спицами: пошаговый мастер-класс", "i": "🧵", "c": "rukodelie-i-diy"}, {"s": "skhemy-shali-kryuchkom-prostye-no-krasivye", "t": "Схемы шали крючком: простые, но красивые узоры для начинающих", "i": "🧵", "c": "rukodelie-i-diy"}, {"s": "skolko-zvezd-u-majora-politsii", "t": "Сколько звезд у майора полиции: погоны и знаки различия", "i": "🪖", "c": "voennaya-forma"}, {"s": "skhema-babochki-kryuchkom", "t": "Схема бабочки крючком: пошаговый мастер-класс", "i": "🧵", "c": "rukodelie-i-diy"}, {"s": "skhema-platka-spitsami", "t": "Схема платка спицами: от простого квадрата до ажурного узора", "i": "🧣", "c": "sharfy-i-platki"}, {"s": "skhema-shapki-kryuchkom-dlya-zhenshchin", "t": "Схема шапки крючком для женщин: от выбора пряжи до фасона", "i": "🧵", "c": "rukodelie-i-diy"}, {"s": "skhema-snyatiya-merok-s-muzhchiny", "t": "Схема снятия мерок с мужчины: пошаговая инструкция", "i": "🧵", "c": "rukodelie-i-diy"}, {"s": "skhemy-string-art", "t": "Схемы стринг арт: мастер-класс для начинающих, шаблоны", "i": "🧵", "c": "rukodelie-i-diy"}, {"s": "skolko-u-lejtenanta-zvezd", "t": "Сколько у лейтенанта звезд: знаки различия и правила ношения", "i": "🪖", "c": "voennaya-forma"}, {"s": "skhema-kardigana-kryuchkom-dlya-zhenshchiny", "t": "Схема кардигана крючком для женщины: пошаговый мастер-класс", "i": "🧵", "c": "rukodelie-i-diy"}, {"s": "skhema-sharfa-kryuchkom", "t": "Схема шарфа крючком: пошаговая инструкция для новичков", "i": "🧣", "c": "sharfy-i-platki"}, {"s": "skhema-vyazaniya-kryuchkom-platka-treugolnika", "t": "Схема вязания крючком платка-треугольника: пошаговое руководство", "i": "🧵", "c": "rukodelie-i-diy"}, {"s": "skhema-vyazannogo-kombinezona-dlya-novorozhdennogo", "t": "Схема вязаного комбинезона для новорожденного спицами", "i": "🧵", "c": "rukodelie-i-diy"}, {"s": "skhemy-vyazaniya-spitsami-uzorov-s-opisaniem-dlya-zhenskoj-kofty", "t": "Схемы вязания спицами узоров с описанием для женской кофты", "i": "🧶", "c": "kofty-i-svitery"}, {"s": "skandinavskij-platok-spitsami-skhema-i-opisanie", "t": "Скандинавский платок спицами: схемы, описание и узоры", "i": "🧵", "c": "rukodelie-i-diy"}, {"s": "skhema-platya-kryuchkom-dlya-kukly", "t": "Схема платья крючком для куклы: пошаговый мастер-класс", "i": "🧵", "c": "rukodelie-i-diy"}, {"s": "skhema-sochetaniya-tsvetov-v-odezhde-dlya-zhenshchin", "t": "Схема сочетания цветов в одежде для женщин: полный гид", "i": "👠", "c": "stil-i-moda"}, {"s": "skolko-den-est-kolgotki", "t": "Сколько дней носить колготки: нормы гигиены и уход", "i": "👙", "c": "nizhnee-belyo-i-kolgotki"}, {"s": "skolko-let-dzhinsam", "t": "Сколько лет джинсам: история создания, эволюция и факты", "i": "👖", "c": "dzhinsy"}, {"s": "skolko-zvezdochek-na-pogonakh-u-lejtenanta", "t": "Сколько звездочек на погонах у лейтенанта: знаки различия", "i": "🪖", "c": "voennaya-forma"}, {"s": "skolzkie-shnurki-razvyazyvayutsya-chto-delat", "t": "Скользкие шнурки развязываются: что делать и как завязать", "i": "👜", "c": "aksessuary"}, {"s": "skhema-vyazaniya-orenburgskogo-platka-spitsami-s-opisaniem-dlya-nachinayushchikh", "t": "Схема вязания оренбургского платка спицами: описание", "i": "🧵", "c": "rukodelie-i-diy"}, {"s": "skhemy-vyazaniya-shnura-kryuchkom", "t": "Схемы вязания шнура крючком: пошаговые инструкции", "i": "🧵", "c": "rukodelie-i-diy"}, {"s": "skhemy-yubok-kryuchkom", "t": "Схемы юбок крючком: подробные инструкции и узоры", "i": "🧵", "c": "rukodelie-i-diy"}, {"s": "skolko-den-byvayut-kolgotki-zhenskie", "t": "Сколько ДЕН женские колготки: таблица плотности и сезоны", "i": "👙", "c": "nizhnee-belyo-i-kolgotki"}, {"s": "skolko-zvezd-na-pogonakh-lejtenanta", "t": "Сколько звезд на погонах лейтенанта: знаки различия РФ", "i": "🪖", "c": "voennaya-forma"}, {"s": "skolko-zvezd-u-generala-lejtenanta", "t": "Сколько звезд у генерал-лейтенанта: погоны РФ и СССР", "i": "🪖", "c": "voennaya-forma"}, {"s": "skhema-vorotnika-kryuchkom", "t": "Схема воротника крючком: пошаговые инструкции и узоры", "i": "🧵", "c": "rukodelie-i-diy"}, {"s": "skhema-vyazaniya-kofty-spitsami-dlya-zhenshchin-s-opisaniem", "t": "Схема вязания кофты спицами для женщин: пошаговое описание", "i": "🧵", "c": "rukodelie-i-diy"}, {"s": "skhema-vyazaniya-noskov-kryuchkom", "t": "Схема вязания носков крючком: пошаговая инструкция", "i": "🧵", "c": "rukodelie-i-diy"}, {"s": "skolko-i-kakogo-razmera-nuzhno-odezhdy-dlya-novorozhdennogo", "t": "Сколько одежды нужно новорожденному: полный список вещей", "i": "🧸", "c": "detskaya-odezhda"}, {"s": "skolko-odnorazovykh-trusov-brat-v-roddom", "t": "Сколько одноразовых трусов брать в роддом: точный расчет", "i": "👙", "c": "nizhnee-belyo-i-kolgotki"}, {"s": "skhema-dlya-vyazaniya-kryuchkom-shapki", "t": "Схема для вязания шапки крючком: пошаговые инструкции", "i": "🧵", "c": "rukodelie-i-diy"}, {"s": "skhema-vyazaniya-kryuchkom-kosynki-dlya-zhenshchin-na-golovu", "t": "Схема вязания косынки крючком для женщин: пошаговый мастер-класс", "i": "🧵", "c": "rukodelie-i-diy"}, {"s": "skiny-dzhinsy-muzhskie", "t": "Мужские скинни: с чем носить, как выбрать и сочетать", "i": "👖", "c": "dzhinsy"}, {"s": "skladka-na-bryukakh", "t": "Складка на брюках: как заутюжить и сохранить стрелки", "i": "🩳", "c": "bryuki-i-shorty"}, {"s": "skolko-medalej-v-ryad-mozhno-veshat-na-paradnuyu-formu", "t": "Сколько медалей в ряд на парадной форме: нормы и правила", "i": "🪖", "c": "voennaya-forma"}, {"s": "skolko-zvezd-na-pogonakh-u-polkovnika-politsii", "t": "Звезды на погонах полковника полиции: количество и расположение", "i": "🪖", "c": "voennaya-forma"}, {"s": "skhema-baktusa-kryuchkom", "t": "Схема бактуса крючком: пошаговая инструкция и узоры", "i": "🧵", "c": "rukodelie-i-diy"}, {"s": "skhema-vyazaniya-kryuchkom-palantina", "t": "Схема вязания крючком палантина: узоры, пряжа и пошаговая инструкция", "i": "🧵", "c": "rukodelie-i-diy"}, {"s": "skladki-na-bryukakh-speredi", "t": "Складки на брюках спереди: зачем нужны и как их носить", "i": "🩳", "c": "bryuki-i-shorty"}, {"s": "skolko-belykh-polosok-na-vorotnike-matrosa-rossijskogo-flota", "t": "Сколько белых полос на воротнике матроса: история и смысл", "i": "🪖", "c": "voennaya-forma"}, {"s": "skolko-medalej-v-ryad-mozhno", "t": "Сколько медалей в ряд можно носить по уставу: нормы и правила", "i": "🪖", "c": "voennaya-forma"}, {"s": "skolko-tkani-nuzhno-na-fartuk", "t": "Сколько ткани нужно на фартук: расход, выкройки и советы", "i": "🧵", "c": "rukodelie-i-diy"}, {"s": "skhema-vyazaniya-kryuchkom-top", "t": "Схема вязания крючком топ: пошаговая инструкция для новичков", "i": "🧵", "c": "rukodelie-i-diy"}, {"s": "skhemy-dlya-sharfa-kryuchkom", "t": "Схемы для шарфа крючком: узоры, инструкции и фото", "i": "🧣", "c": "sharfy-i-platki"}, {"s": "skhema-kak-zavyazat-shnurki", "t": "Как завязать шнурки: схемы, узлы и способы", "i": "👜", "c": "aksessuary"}, {"s": "skhema-shalej-spitsami", "t": "Схема шалей спицами: узоры, размеры и пошаговые инструкции", "i": "🧣", "c": "sharfy-i-platki"}, {"s": "skhemy-shalej-spitsami", "t": "Схемы шалей спицами: узоры, инструкции и фото", "i": "🧣", "c": "sharfy-i-platki"}, {"s": "skladki-na-kurtke", "t": "Складки на куртке: как расправить, ушить или сделать своими руками", "i": "🧼", "c": "ukhod-za-odezhdoj"}, {"s": "skolko-zvezdochek-u-starshego-lejtenanta-na-pogonakh", "t": "Сколько звездочек у старшего лейтенанта: погоны и форма", "i": "🪖", "c": "voennaya-forma"}, {"s": "skhema-shali-kryuchkom-dlya-nachinayushchikh-samaya-prostaya", "t": "Схема шали крючком для начинающих: пошаговый урок", "i": "🧵", "c": "rukodelie-i-diy"}, {"s": "skhema-zavyazyvaniya-galstuka-muzhskogo-v-kartinkakh-klassika-dvojnoj-uzel", "t": "Двойной узел галстука: пошаговая схема завязывания с фото", "i": "👜", "c": "aksessuary"}, {"s": "skhemy-vyazaniya-dlya-kukol", "t": "Схемы вязания для кукол: подбор пряжи, техники и узоры", "i": "🧵", "c": "rukodelie-i-diy"}, {"s": "skhemy-zavyazyvaniya-shnurkov", "t": "Схемы завязывания шнурков: 7 способов для обуви и стиля", "i": "👜", "c": "aksessuary"}, {"s": "skinni-dzhinsy-eto-kakie", "t": "Скинни джинсы это какие: отличия, фасоны и с чем носить", "i": "👖", "c": "dzhinsy"}, {"s": "skolko-petel-nabirat-na-zhilet", "t": "Сколько петель набирать на жилет: точный расчет", "i": "🧵", "c": "rukodelie-i-diy"}, {"s": "skolko-zvezdochek-u-polkovnika-na-pogonakh", "t": "Сколько звездочек у полковника на погонах: разбор знаков различия", "i": "🪖", "c": "voennaya-forma"}, {"s": "skhema-azhurnogo-uzora-spitsami-dlya-koftochki", "t": "Схема ажурного узора спицами для кофточки: пошагово", "i": "🧶", "c": "kofty-i-svitery"}, {"s": "skhema-dlya-shali", "t": "Схема для шали: как связать, узоры и советы", "i": "🧵", "c": "rukodelie-i-diy"}, {"s": "skhema-namatyvaniya-portyanok", "t": "Схема наматывания портянок: пошаговая инструкция", "i": "🪖", "c": "voennaya-forma"}, {"s": "skhema-vyazaniya-kryuchkom-kofta", "t": "Схема вязания крючком кофты: пошаговый мастер-класс", "i": "🧵", "c": "rukodelie-i-diy"}, {"s": "skhema-vyazaniya-topa-kryuchkom", "t": "Схема вязания топа крючком: пошаговый мастер-класс для начинающих", "i": "🧵", "c": "rukodelie-i-diy"}, {"s": "skinni-dzhinsy-chernye-zhenskie", "t": "Скинни джинсы черные женские: гид по выбору и стилю", "i": "👖", "c": "dzhinsy"}, {"s": "skinni-dzhinsy-na-parne", "t": "Скинни джинсы на парне: как носить и сочетать", "i": "👖", "c": "dzhinsy"}, {"s": "skolko-po-vremeni-vyazat-sviter", "t": "Сколько по времени вязать свитер: расчет часов и дней", "i": "🧵", "c": "rukodelie-i-diy"}, {"s": "skolko-zvezd-u-mladshego-lejtenanta-na-pogonakh-v-politsii", "t": "Сколько звезд у младшего лейтенанта полиции: знаки различия", "i": "🪖", "c": "voennaya-forma"}, {"s": "skolko-zvezdochek-u-podpolkovnika", "t": "Сколько звездочек у подполковника: знаки различия", "i": "🪖", "c": "voennaya-forma"}, {"s": "skolzyashchij-uzel-dlya-shnurkov-na-krossovkakh", "t": "Скользящий узел для шнурков: схемы, виды и способы завязывания", "i": "👟", "c": "obuv"}, {"s": "skhema-shlyapy-kryuchkom", "t": "Схема шляпы крючком: пошаговый мастер-класс для новичков", "i": "🧵", "c": "rukodelie-i-diy"}, {"s": "skhema-vyazaniya-manishki-spitsami", "t": "Схема вязания манишки спицами: пошаговая инструкция для начинающих", "i": "🧵", "c": "rukodelie-i-diy"}, {"s": "skhema-vyazaniya-shapki-bini", "t": "Схема вязания шапки бини спицами: пошаговая инструкция", "i": "🧵", "c": "rukodelie-i-diy"}, {"s": "skinni-dzhinsy-eto-chto-takoe", "t": "Скинни джинсы: что это такое, кому идут и с чем носить", "i": "👖", "c": "dzhinsy"}, {"s": "skinny-fit-dzhinsy-muzhskie-chto-eto", "t": "Мужские джинсы Skinny Fit: что это, кому идут и с чем носить", "i": "👖", "c": "dzhinsy"}, {"s": "skrepki-dlya-odezhdy-nazvanie", "t": "Скрепки для одежды: названия, виды и применение", "i": "🧵", "c": "rukodelie-i-diy"}, {"s": "skhema-vyazaniya-detskoj-koftochki-spitsami", "t": "Схема вязания детской кофточки спицами: инструкции для начинающих", "i": "🧵", "c": "rukodelie-i-diy"}, {"s": "skhema-vyazaniya-kryuchkom-zhileta-dlya-zhenshchin", "t": "Схема вязания крючком женского жилета: пошаговая инструкция", "i": "🧵", "c": "rukodelie-i-diy"}, {"s": "skolko-medalej-mozhno-veshat-v-odin-ryad-na-paradnyj-kitel", "t": "Сколько медалей вешать в ряд на парадный китель: нормы", "i": "🪖", "c": "voennaya-forma"}, {"s": "skolko-tkani-nuzhno-na-shorty", "t": "Сколько ткани нужно на шорты: точный расчет расхода", "i": "🩳", "c": "bryuki-i-shorty"}, {"s": "skhema-dlya-zavyazyvaniya-galstuka", "t": "Схема завязывания галстука: пошаговые инструкции", "i": "👜", "c": "aksessuary"}, {"s": "skhema-vyazaniya-kryuchkom-kofty-setki", "t": "Схема вязания кофты сетки крючком: мастер-класс и советы", "i": "🧵", "c": "rukodelie-i-diy"}, {"s": "skhemy-vyazaniya-shapok-kryuchkom", "t": "Схемы вязания шапок крючком: от новичка до профи", "i": "🧵", "c": "rukodelie-i-diy"}, {"s": "skolko-zvezd-u-serzhanta", "t": "Сколько звезд у сержанта: виды погон и правила ношения", "i": "🪖", "c": "voennaya-forma"}, {"s": "skhema-galstuk-babochka", "t": "Схема галстук-бабочка: пошаговая инструкция завязывания", "i": "👜", "c": "aksessuary"}, {"s": "skhemy-vyazaniya-kryuchkom-sviter", "t": "Схемы вязания крючком свитера: от выбора пряжи до сборки", "i": "🧵", "c": "rukodelie-i-diy"}, {"s": "skhemy-vyazaniya-kryuchkom-vorotnichkov", "t": "Схемы вязания воротничков крючком: пошаговые инструкции и узоры", "i": "🧵", "c": "rukodelie-i-diy"}, {"s": "skhemy-vyazaniya-spitsami-azhurnykh-uzorov-letnikh-koftochek", "t": "Схемы вязания спицами ажурных кофточек: выбор узоров для лета", "i": "🧵", "c": "rukodelie-i-diy"}, {"s": "skinni-fit-chto-eto", "t": "Скинни фит: что это, кому идет и как выбрать идеальные джинсы", "i": "👖", "c": "dzhinsy"}]