[{"s": "zelenoe-vechernee-plate", "t": "Зеленое вечернее платье: оттенки, сочетания и стиль", "i": "👗", "c": "platya-i-sarafany"}, {"s": "zelenoe-plate-kombinatsiya-s-chem-nosit", "t": "Зеленое платье-комбинация: с чем носить, стили, образы", "i": "👗", "c": "platya-i-sarafany"}, {"s": "zelenyj-tsvet-sochetanie-s-drugimi-tsvetami-v-odezhde-dlya-zhenshchin", "t": "Зеленый цвет в одежде: идеальные сочетания для женщин", "i": "👠", "c": "stil-i-moda"}, {"s": "zeleno-izumrudnyj-tsvet", "t": "Зелено изумрудный цвет: сочетания, оттенки и психология в моде", "i": "👠", "c": "stil-i-moda"}, {"s": "zelenyj-s-chem-sochetaetsya-v-odezhde", "t": "С чем носить зеленый: сочетания в одежде и стильные образы", "i": "👠", "c": "stil-i-moda"}, {"s": "zelenoe-plate-s-chem-nosit-obuv", "t": "Зеленое платье с чем носить обувь: гид по сочетаниям", "i": "👠", "c": "stil-i-moda"}, {"s": "zelenyj-tsvet-izumrud", "t": "Зеленый цвет изумруд: сочетания в одежде, макияж и уход", "i": "👠", "c": "stil-i-moda"}, {"s": "zelenyj-tsvet-u-tatar", "t": "Зеленый цвет у татар: символика в национальном костюме", "i": "👘", "c": "natsionalnaya-i-istoricheskaya-odezhda"}, {"s": "zelenoe-plate-s-kakim-tsvetom-sochetaetsya", "t": "Зеленое платье: с чем носить и сочетать (фото и советы)", "i": "👗", "c": "platya-i-sarafany"}, {"s": "zelenaya-futbolka-s-chem-sochetaetsya", "t": "С чем носить зеленую футболку: 25+ идей для стильного образа", "i": "👕", "c": "futbolki-i-topy"}, {"s": "zelenyj-beret-kakie-vojska", "t": "Зеленый берет: какие войска носят, история и отличия", "i": "🪖", "c": "voennaya-forma"}, {"s": "zelenyj-tsvet-bolotnyj", "t": "Зеленый болотный цвет в одежде: сочетания и оттенки", "i": "👠", "c": "stil-i-moda"}, {"s": "zelenye-berety-u-kakikh-vojsk", "t": "Зеленые береты: у каких войск и как носить", "i": "📁", "c": null}, {"s": "zelenyj-tsvet-komu-idet", "t": "Зеленый цвет в одежде: кому идет, оттенки и сочетания", "i": "📁", "c": null}, {"s": "zelenyj-khaki-s-kakim-tsvetom-sochetaetsya", "t": "С чем носить зеленый хаки: 30+ идей для стильного образа", "i": "👠", "c": "stil-i-moda"}, {"s": "zelenyj-tsvet-s-chem-sochetaetsya-v-odezhde", "t": "Зеленый цвет в одежде: с чем носить и сочетать", "i": "👠", "c": "stil-i-moda"}, {"s": "zelenyj-beret-vv", "t": "Зеленый берет ВВ: история, ношение, отбивка и уход", "i": "🪖", "c": "voennaya-forma"}, {"s": "zelenye-strelki-makiyazh", "t": "Зеленые стрелки в макияже: как подобрать и нанести", "i": "👠", "c": "stil-i-moda"}, {"s": "zelenyj-bolotnyj-tsvet-s-chem-sochetaetsya-v-odezhde", "t": "Зеленый болотный цвет в одежде: с чем сочетать и как носить", "i": "👠", "c": "stil-i-moda"}, {"s": "zelenyj-pidzhak-v-kletku", "t": "Зеленый пиджак в клетку: с чем носить, фасоны и сочетания", "i": "🤵", "c": "pidzhaki-i-kostyumy"}, {"s": "zelenyj-beret-chej", "t": "Зеленый берет: чей он, история и как носить", "i": "🪖", "c": "voennaya-forma"}, {"s": "zelenyj-tsvet-s-kakim-tsvetom-sochetaetsya-v-odezhde", "t": "С чем носить зеленый: гид по сочетаниям в одежде", "i": "👠", "c": "stil-i-moda"}, {"s": "zelenyj-tsvet-s-kakim-sochetaetsya-v-odezhde-dlya-zhenshchin", "t": "С чем носить зеленый: сочетания в одежде для женщин", "i": "👠", "c": "stil-i-moda"}, {"s": "zelenye-berety-eto-kakie-vojska", "t": "Зеленые береты: какие войска носят, история и стиль", "i": "🪖", "c": "voennaya-forma"}, {"s": "zelenyj-niz-kakoj-verkh", "t": "Зеленый низ, какой верх: лучшие сочетания для стильного образа", "i": "👠", "c": "stil-i-moda"}, {"s": "zelenyj-tsvet-v-odezhde-sochetanie-s-drugimi-tsvetami", "t": "Зеленый цвет в одежде: лучшие сочетания и стиль", "i": "👠", "c": "stil-i-moda"}, {"s": "zelenyj-s-kakim-tsvetom-sochetaetsya-v-odezhde-dlya-zhenshchin", "t": "Зеленый цвет в одежде: идеальные сочетания для женщин", "i": "👠", "c": "stil-i-moda"}, {"s": "zelenoe-plate-makiyazh", "t": "Макияж к зеленому платью: секреты идеального образа", "i": "👠", "c": "stil-i-moda"}]